Workbook

Sheet Dashboard
I6: Britannia Industries is one of the Indias leading food companies | S6: with 100 year of legacy and annual revenues in | AA6: excess of Rs. 16000 Cr. Britannia is among the most trusted food brands,
I7: and manufacturers Indias favourite brands like Good Day, Tiger, Nutrichoice | U7: ,Milk Bikis and Marie Gold and many more . Britannia's product portfolio includes Biscuits , Bread , Cakes , Rusk,
S8: and dairy products inlcluding Cheese , Beverages ,Milk and Yogurt.
J10: Company Registered Name : Britannia Industries Limited | U10: Sector: FMCG | Y10: TICKER: BRITANNIA | AD10: BSE CODE: 500825 | AI10: CMP: 6106

Sheet About
B10: Peer companies
E12: Name of Company | L12: Country | O12: CMP | R12: Market Capital | U12: Revenue Growth (%) | AA12: Profit Growth (%)
E14: Nestle India | L14: India | O14: 1293.8 | R14: 249485.31 | W14: 9.74 | AB14: 1.34
E15: Bikaji Foods | L15: India | O15: 635.35 | R15: 15921.41 | W15: 9.98 | AB15: -8.31
E16: Zydus Wellness | L16: India | O16: 52.83 | R16: 12702.57 | W16: 31.45 | AB16: -24.89
E17: Gopal Snacks | L17: India | O17: 311.55 | R17: 3882.61 | W17: -6.17 | AB17: -58.17
E18: Mrs Bectors | L18: India | O18: 216.65 | R18: 6650.95 | W18: 8.93 | AB18: -4.06
B21: Shareholding pattern
E23: Investors | M23: 2025 | S23: Major Shareholders
E24: Shareholders | J24: March | L24: June | N24: Septemer | P24: December
E26: Promoters | J26: 0.5055 | L26: 0.5055 | N26: 0.5055 | P26: 0.5055 | R26: Promoters | S26: Associated Biscuits International Limited
E27: FIIs | J27: 0.1572 | L27: 0.1558 | N27: 0.1502 | P27: 0.1488 | R27: FIIs | S27: J P Morgan Funds
E28: DIIs | J28: 0.1826 | L28: 0.1865 | N28: 0.1939 | P28: 0.1955 | R28: DIIs | S28: Lici New Endowment Plus-Secured Fund
E29: Government | J29: 0 | L29: 0.0001 | N29: 0.0001 | P29: 0.0003
E30: Public | J30: 0.1548 | L30: 0.152 | N30: 0.1503 | P30: 0.1497
B34: Recent Updates
E36: Financial Performance: Q3 FY26 net profit rose 17% to ₹680 crore, with revenue increasing 9.5%.
E38: Leadership Change: Rakshit Hargave was appointed CEO and MD to drive growth.
E40: Strategic Focus: Adopting a "startup mentality" to unlock "resident jewels" (smaller brands) to boost margins.
E42: Stock Trend: As of Feb 20, 2026, the stock has experienced a minor, temporary downward trend (down -0.17% to ₹6,098.50) following recent highs.
E44: Input Costs: Operating with, softened input costs, boosting margins.
E46: Growth Strategy: Focus on urban consumption, which is showing signs of recovery after being dull.
E48: Market Position: Remains a top FMCG pick with a market cap of over ₹1,46,000

Sheet Balance Sheet
B1: Britannia Industries Limited
B2: BALANCE SHEET
B4: Particulars | C4: 2019 | D4: 2020 | E4: 2021 | F4: 2022 | G4: 2023 | H4: 2024 | I4: 2025 | J4: 2026 | K4: 2027 | L4: 2028 | M4: 2029 | N4: 2030 | O4: 2031 | P4: 2032
C5: Actual | D5: Actual | E5: Actual | F5: Actual | G5: Actual | H5: Actual | I5: Actual | J5: Forecast | K5: Forecast | L5: Forecast | M5: Forecast | N5: Forecast | O5: Forecast | P5: Forecast
A6: I | B6: ASSETS
A7: 1 | B7: Non-current assets
B8: (a) Property, plant and equipment | C8: 1535.58 | D8: 1716.37 | E8: 1634.3 | F8: 1584.05 | G8: 2472.19 | H8: 2602.94 | I8: 2734.61 | J8: ='Asset Schedule'!J40 -> 2493.7754 | K8: ='Asset Schedule'!K40 -> 2426.4029 | L8: ='Asset Schedule'!L40 -> 2404.0222 | M8: ='Asset Schedule'!M40 -> 2435.9469 | N8: ='Asset Schedule'!N40 -> 2529.5293 | O8: ='Asset Schedule'!O40 -> 2686.1088 | P8: ='Asset Schedule'!P40 -> 2918.4263
B9: (b) Capital work-in-progress | C9: 101.24 | D9: 39.55 | E9: 116.52 | F9: 535.68 | G9: 105 | H9: 187.54 | I9: 89.2 | J9: ='Asset Schedule'!J41 -> 209.85024 | K9: ='Asset Schedule'!K41 -> 204.18087 | L9: ='Asset Schedule'!L41 -> 202.29755 | M9: ='Asset Schedule'!M41 -> 204.984 | N9: ='Asset Schedule'!N41 -> 212.85892 | O9: ='Asset Schedule'!O41 -> 226.03502 | P9: ='Asset Schedule'!P41 -> 245.58446
B10: (c) Investment property | C10: 14.73 | D10: 14.47 | E10: 14.21 | F10: 13.95 | G10: 40.63 | H10: 27.48 | I10: 28.9 | J10: ='Asset Schedule'!J42 -> 26.162712 | K10: ='Asset Schedule'!K42 -> 25.455893 | L10: ='Asset Schedule'!L42 -> 25.221093 | M10: ='Asset Schedule'!M42 -> 25.556022 | N10: ='Asset Schedule'!N42 -> 26.537814 | O10: ='Asset Schedule'!O42 -> 28.180522 | P10: ='Asset Schedule'!P42 -> 30.617813
B11: (d) Goodwill | C11: 130.37 | D11: 138.97 | E11: 135.9 | F11: 139.61 | G11: 128.16 | H11: 129.82 | I11: 132.78 | J11: =I11 -> 132.78 | K11: =J11 -> 132.78 | L11: =K11 -> 132.78 | M11: =L11 -> 132.78 | N11: =M11 -> 132.78 | O11: =N11 -> 132.78 | P11: =O11 -> 132.78
B12: (e) Other intangible assets | C12: 7.62 | D12: 8.37 | E12: 8.54 | F12: 15.6 | G12: 14.24 | H12: 10.9 | I12: 7.51 | J12: ='Asset Schedule'!J43 -> 13.032553 | K12: ='Asset Schedule'!K43 -> 12.680462 | L12: ='Asset Schedule'!L43 -> 12.5635 | M12: ='Asset Schedule'!M43 -> 12.730339 | N12: ='Asset Schedule'!N43 -> 13.219404 | O12: ='Asset Schedule'!O43 -> 14.037693 | P12: ='Asset Schedule'!P43 -> 15.251793
B13: (f) Investment in associates | C13: 1.04 | D13: 1.48 | E13: 2.29 | F13: 2.09 | G13: 495.16 | H13: 491.96 | I13: 483.62 | J13: =I13 -> 483.62 | K13: =J13 -> 483.62 | L13: =K13 -> 483.62 | M13: =L13 -> 483.62 | N13: =M13 -> 483.62 | O13: =N13 -> 483.62 | P13: =O13 -> 483.62
B14: (g) Financial assets
B15: (i) Investments | C15: 725.36 | D15: 1882.98 | E15: 1385.15 | F15: 926.55 | G15: 1028.09 | H15: 578.25 | I15: 1270.17 | J15: =I15 -> 1270.17 | K15: =J15 -> 1270.17 | L15: =K15 -> 1270.17 | M15: =L15 -> 1270.17 | N15: =M15 -> 1270.17 | O15: =N15 -> 1270.17 | P15: =O15 -> 1270.17
B16: (ii) Loans receivable | C16: 19.02 | D16: 202.95 | E16: 74.58 | F16: 100 | G16: 150 | H16: 0 | I16: 25 | J16: =I16 -> 25 | K16: =J16 -> 25 | L16: =K16 -> 25 | M16: =L16 -> 25 | N16: =M16 -> 25 | O16: =N16 -> 25 | P16: =O16 -> 25
B17: (iii) Other financial assets | C17: 28.67 | D17: 31.33 | E17: 30.13 | F17: 31.8 | G17: 23.57 | H17: 25.5 | I17: 28.19 | J17: =I17 -> 28.19 | K17: =J17 -> 28.19 | L17: =K17 -> 28.19 | M17: =L17 -> 28.19 | N17: =M17 -> 28.19 | O17: =N17 -> 28.19 | P17: =O17 -> 28.19
B18: (h) Deferred tax assets, (net) | C18: 13.75 | D18: 19.56 | E18: 9.66 | F18: 51.67 | G18: 57.25 | H18: 43.88 | I18: 36.59 | J18: =I18 -> 36.59 | K18: =J18 -> 36.59 | L18: =K18 -> 36.59 | M18: =L18 -> 36.59 | N18: =M18 -> 36.59 | O18: =N18 -> 36.59 | P18: =O18 -> 36.59
B19: (i) Income-tax assets, (net) | C19: 37.02 | D19: 68.77 | E19: 71.84 | F19: 44.93 | G19: 43.64 | H19: 67.95 | I19: 46.26 | J19: =I19 -> 46.26 | K19: =J19 -> 46.26 | L19: =K19 -> 46.26 | M19: =L19 -> 46.26 | N19: =M19 -> 46.26 | O19: =N19 -> 46.26 | P19: =O19 -> 46.26
B20: (j) Other non-current assets | C20: 101.08 | D20: 42.46 | E20: 105.98 | F20: 99.18 | G20: 48.56 | H20: 58.68 | I20: 42.04 | J20: =I20 -> 42.04 | K20: =J20 -> 42.04 | L20: =K20 -> 42.04 | M20: =L20 -> 42.04 | N20: =M20 -> 42.04 | O20: =N20 -> 42.04 | P20: =O20 -> 42.04
B21: Total non-current assets | C21: =SUM(C8:C20) -> 2715.48 | D21: =SUM(D8:D20) -> 4167.26 | E21: =SUM(E8:E20) -> 3589.1 | F21: =SUM(F8:F20) -> 3545.11 | G21: =SUM(G8:G20) -> 4606.49 | H21: =SUM(H8:H20) -> 4224.9 | I21: =SUM(I8:I20) -> 4924.87 | J21: =SUM(J8:J20) -> 4807.4709 | ... P21: =SUM(P8:P20) -> 5274.5304
A23: 2 | B23: Current assets
B24: (a) Inventories | C24: 781.38 | D24: 740.96 | E24: 1091.49 | F24: 1367.49 | G24: 1193.26 | H24: 1181.22 | I24: 1236.51 | J24: ='Working Capital Schedule'!J11 -> 1527.6793 | K24: ='Working Capital Schedule'!K11 -> 1626.7369 | L24: ='Working Capital Schedule'!L11 -> 1673.1872 | M24: ='Working Capital Schedule'!M11 -> 2030.8365 | N24: ='Working Capital Schedule'!N11 -> 2250.8721 | O24: ='Working Capital Schedule'!O11 -> 2470.0177 | P24: ='Working Capital Schedule'!P11 -> 2783.9632
B25: (b) Financial assets
B26: (i) Investments | C26: 749.88 | D26: 1008.77 | E26: 1393.25 | F26: 833.73 | G26: 1800.99 | H26: 1696.51 | I26: 1111.64 | J26: =I26 -> 1111.64 | K26: =J26 -> 1111.64 | L26: =K26 -> 1111.64 | M26: =L26 -> 1111.64 | N26: =M26 -> 1111.64 | O26: =N26 -> 1111.64 | P26: =O26 -> 1111.64
B27: (ii) Trade receivables | C27: 394.24 | D27: 320.36 | E27: 257.27 | F27: 331.93 | G27: 328.94 | H27: 393.33 | I27: 448.61 | J27: ='Working Capital Schedule'!J24 -> 428.67911 | K27: ='Working Capital Schedule'!K24 -> 522.88797 | L27: ='Working Capital Schedule'!L24 -> 517.30271 | M27: ='Working Capital Schedule'!M24 -> 629.45323 | N27: ='Working Capital Schedule'!N24 -> 646.5336 | O27: ='Working Capital Schedule'!O24 -> 787.62691 | P27: ='Working Capital Schedule'!P24 -> 842.09291
B28: (iii) Cash and cash equivalents | C28: 60.32 | D28: 81.23 | E28: 142.74 | F28: 117.99 | G28: 102.38 | H28: 322.8 | I28: 132.78 | J28: =CFS!J64 -> 1818.16 | K28: =CFS!K64 -> 4163.21 | L28: =CFS!L64 -> 7648.45 | M28: =CFS!M64 -> 12739.52 | N28: =CFS!N64 -> 18896.2 | O28: =CFS!O64 -> 28895.25 | P28: =CFS!P64 -> 44241.37
B29: (iv) Bank balances other than (iii) above | C29: 49.5 | D29: 41.62 | E29: 68.6 | F29: 66.91 | G29: 95.6 | H29: 123.55 | I29: 179.7 | J29: =I29 -> 179.7 | K29: =J29 -> 179.7 | L29: =K29 -> 179.7 | M29: =L29 -> 179.7 | N29: =M29 -> 179.7 | O29: =N29 -> 179.7 | P29: =O29 -> 179.7
B30: (v) Loans receivable | C30: 1203.92 | D30: 1110.11 | E30: 946.56 | F30: 698 | G30: 560 | H30: 460 | I30: 50 | J30: =I30 -> 50 | K30: =J30 -> 50 | L30: =K30 -> 50 | M30: =L30 -> 50 | N30: =M30 -> 50 | O30: =N30 -> 50 | P30: =O30 -> 50
B31: (vi) Other financial assets | C31: 126.29 | D31: 229.75 | E31: 397.76 | F31: 428.03 | G31: 451.96 | H31: 531.13 | I31: 630.46 | J31: =I31 -> 630.46 | K31: =J31 -> 630.46 | L31: =K31 -> 630.46 | M31: =L31 -> 630.46 | N31: =M31 -> 630.46 | O31: =N31 -> 630.46 | P31: =O31 -> 630.46
B32: (c) Other current assets | C32: 160.81 | D32: 142.17 | E32: 122.01 | F32: 138.22 | G32: 180.74 | H32: 133.71 | I32: 123.98 | J32: =I32 -> 123.98 | K32: =J32 -> 123.98 | L32: =K32 -> 123.98 | M32: =L32 -> 123.98 | N32: =M32 -> 123.98 | O32: =N32 -> 123.98 | P32: =O32 -> 123.98
B33: (d) Assets held for sale | E33: 0 | F33: 0 | G33: 32.36 | H33: 6.41 | I33: 0 | J33: =I33 -> 0 | K33: =J33 -> 0 | L33: =K33 -> 0 | M33: =L33 -> 0 | N33: =M33 -> 0 | O33: =N33 -> 0 | P33: =O33 -> 0
B34: Total current assets | C34: =SUM(C24:C32) -> 3526.34 | D34: =SUM(D24:D32) -> 3674.97 | E34: =SUM(E24:E33) -> 4419.68 | F34: =SUM(F24:F33) -> 3982.3 | G34: =SUM(G24:G33) -> 4746.23 | H34: =SUM(H24:H33) -> 4848.66 | I34: =SUM(I24:I33) -> 3913.68 | J34: =SUM(J24:J32) -> 5870.2984 | K34: =SUM(K24:K32) -> 8408.6148 | L34: =SUM(L24:L32) -> 11934.72 | M34: =SUM(M24:M32) -> 17495.59 | N34: =SUM(N24:N32) -> 23889.386 | O34: =SUM(O24:O32) -> 34248.675 | P34: =SUM(P24:P32) -> 49963.206
B36: Total Assets (I) | C36: =SUM(C21+C34) -> 6241.82 | D36: =SUM(D21+D34) -> 7842.23 | E36: =SUM(E21+E34) -> 8008.78 | F36: =SUM(F21+F34) -> 7527.41 | G36: =SUM(G21+G34) -> 9352.72 | H36: =SUM(H21+H34) -> 9073.56 | I36: =SUM(I21+I34) -> 8838.55 | J36: =SUM(J21+J34) -> 10677.769 | ... P36: =SUM(P21+P34) -> 55237.737
A38: II | B38: EQUITY AND LIABILITIES
A39: A | B39: Equity Shareholde's fund
B40: (a) Equity share capital | C40: 24.03 | D40: 24.05 | E40: 24.09 | F40: 24.09 | G40: 24.09 | H40: 24.09 | I40: 24.09 | J40: =I40 -> 24.09 | K40: =J40 -> 24.09 | L40: =K40 -> 24.09 | M40: =L40 -> 24.09 | N40: =M40 -> 24.09 | O40: =N40 -> 24.09 | P40: =O40 -> 24.09
B41: (b) Reserves and Surplus | C41: 4229.22 | D41: 4378.78 | E41: 3523.57 | F41: 2534.01 | G41: 3510.18 | H41: 3917.43 | I41: 4331.63 | J41: =I41+'Income Statement'!J38+CFS!J57 -> 5405.9743 | K41: =J41+'Income Statement'!K38+CFS!K57 -> 6631.9513 | L41: =K41+'Income Statement'!L38+CFS!L57 -> 8919.9366 | M41: =L41+'Income Statement'!M38+CFS!M57 -> 11633.993 | N41: =M41+'Income Statement'!N38+CFS!N57 -> 14673.31 | O41: =N41+'Income Statement'!O38+CFS!O57 -> 19129.339 | P41: =O41+'Income Statement'!P38+CFS!P57 -> 25858.743
B42: Total share capital | C42: =SUM(C40:C41) -> 4253.25 | D42: =SUM(D40:D41) -> 4402.83 | E42: =SUM(E40:E41) -> 3547.66 | F42: =SUM(F40:F41) -> 2558.1 | G42: =SUM(G40:G41) -> 3534.27 | H42: =SUM(H40:H41) -> 3941.52 | I42: =SUM(I40:I41) -> 4355.72 | J42: =SUM(J40:J41) -> 5430.0643 | ... P42: =SUM(P40:P41) -> 25882.833
B43: Non-controlling interests | C43: 32.68 | D43: 35.65 | E43: 36.34 | F43: 27.5 | G43: 30.23 | H43: 24.5 | I43: 25.6 | J43: =I43 -> 25.6 | K43: =J43 -> 25.6 | L43: =K43 -> 25.6 | M43: =L43 -> 25.6 | N43: =M43 -> 25.6 | O43: =N43 -> 25.6 | P43: =O43 -> 25.6
B44: Total equity | C44: =SUM(C42:C43) -> 4285.93 | D44: =SUM(D42:D43) -> 4438.48 | E44: =SUM(E42:E43) -> 3584 | F44: =SUM(F42:F43) -> 2585.6 | G44: =SUM(G42:G43) -> 3564.5 | H44: =SUM(H42:H43) -> 3966.02 | I44: =SUM(I42:I43) -> 4381.32 | J44: =SUM(J42:J43) -> 5455.6643 | ... P44: =SUM(P42:P43) -> 25908.433
A46: B | B46: Liabilities
A47: 1 | B47: Non-current liabilities
B48: (a) Financial Liabilities
B49: (i) Borrowings | C49: 61.92 | D49: 766.06 | E49: 747.75 | F49: 706.99 | G49: 1551.8 | H49: 904.72 | I49: 712.94 | J49: ='Debt Schedule'!J15 -> 1006.3023 | K49: ='Debt Schedule'!K15 -> 1319.7246 | L49: ='Debt Schedule'!L15 -> 1657.8317 | M49: ='Debt Schedule'!M15 -> 2026.4159 | N49: ='Debt Schedule'!N15 -> 2432.8094 | O49: ='Debt Schedule'!O15 -> 2886.3974 | P49: ='Debt Schedule'!P15 -> 3399.3367
B50: (ii) Other financial liabilities | C50: 27.24 | D50: 46.54 | E50: 54.07 | F50: 13.76 | G50: 14.36 | H50: 20.13 | I50: 19.45 | J50: =I50 -> 19.45 | K50: =J50 -> 19.45 | L50: =K50 -> 19.45 | M50: =L50 -> 19.45 | N50: =M50 -> 19.45 | O50: =N50 -> 19.45 | P50: =O50 -> 19.45
B51: (b) Deferred tax liabilities, (net) | C51: 3.87 | D51: 12.69 | E51: 8.69 | F51: 52.64 | G51: 60.15 | H51: 65.66 | I51: 72.21 | J51: =I51 -> 72.21 | K51: =J51 -> 72.21 | L51: =K51 -> 72.21 | M51: =L51 -> 72.21 | N51: =M51 -> 72.21 | O51: =N51 -> 72.21 | P51: =O51 -> 72.21
B52: (c) Other long-Term borrowings | C52: 0 | D52: 0 | E52: 0 | F52: 0.81 | G52: 1.87 | H52: 2.06 | I52: 1.8 | J52: =I52 -> 1.8 | K52: =J52 -> 1.8 | L52: =K52 -> 1.8 | M52: =L52 -> 1.8 | N52: =M52 -> 1.8 | O52: =N52 -> 1.8 | P52: =O52 -> 1.8
B53: (d) Long term provisions | C53: 11.45 | D53: 0 | E53: 0 | F53: 20.47 | G53: 25.64 | H53: 30.56 | I53: 32.57 | J53: =I53 -> 32.57 | K53: =J53 -> 32.57 | L53: =K53 -> 32.57 | M53: =L53 -> 32.57 | N53: =M53 -> 32.57 | O53: =N53 -> 32.57 | P53: =O53 -> 32.57
B54: Total non-current liabilities | C54: =SUM(C48:C53) -> 104.48 | D54: =SUM(D48:D53) -> 825.29 | E54: =SUM(E48:E53) -> 810.51 | F54: =SUM(F48:F53) -> 794.67 | G54: =SUM(G48:G53) -> 1653.82 | H54: =SUM(H48:H53) -> 1023.13 | I54: =SUM(I48:I53) -> 838.97 | J54: =SUM(J48:J53) -> 1132.3323 | ... P54: =SUM(P48:P53) -> 3525.3667
A56: 2 | B56: Current liabilities
B57: (a) Trade payables
B58: (i) total outstanding dues of micro enterprises and small enterprises | C58: 1.78 | D58: 8.53 | E58: 28.44 | F58: 62.76 | G58: 43.92 | H58: 30.83 | I58: 27.83 | J58: ='Working Capital Schedule'!J49 -> 38.354995 | K58: ='Working Capital Schedule'!K49 -> 44.846744 | L58: ='Working Capital Schedule'!L49 -> 41.556402 | M58: ='Working Capital Schedule'!M49 -> 57.040836 | N58: ='Working Capital Schedule'!N49 -> 58.245974 | O58: ='Working Capital Schedule'!O49 -> 69.242035 | P58: ='Working Capital Schedule'!P49 -> 70.880086
B59: (ii) total outstanding dues of creditors other than micro enterprises an | C59: 1138.73 | D59: 1038.47 | E59: 1286.31 | F59: 1260.05 | G59: 1404.89 | H59: 1596.65 | I59: 1724.4 | J59: ='Working Capital Schedule'!J50 -> 1827.1048 | K59: ='Working Capital Schedule'!K50 -> 2136.3502 | L59: ='Working Capital Schedule'!L50 -> 1979.6092 | M59: ='Working Capital Schedule'!M50 -> 2717.2363 | N59: ='Working Capital Schedule'!N50 -> 2774.6451 | O59: ='Working Capital Schedule'!O50 -> 3298.4609 | P59: ='Working Capital Schedule'!P50 -> 3376.4923
B60: (b) Lease liabilities | F60: 1.9 | G60: 2.5 | H60: 3.62 | I60: 2.29 | J60: =I60 -> 2.29 | K60: =J60 -> 2.29 | L60: =K60 -> 2.29 | M60: =L60 -> 2.29 | N60: =M60 -> 2.29 | O60: =N60 -> 2.29 | P60: =O60 -> 2.29
B61: (c) Other current liabilities | C61: 95.22 | D61: 150.08 | E61: 140.54 | F61: 130.73 | G61: 176.34 | H61: 167.29 | I61: 194.7 | J61: =I61 -> 194.7 | K61: =J61 -> 194.7 | L61: =K61 -> 194.7 | M61: =L61 -> 194.7 | N61: =M61 -> 194.7 | O61: =N61 -> 194.7 | P61: =O61 -> 194.7
B62: (d) Short-term provisions | C62: 196.51 | D62: 273.7 | E62: 387.47 | F62: 464.64 | G62: 513.39 | H62: 559.2 | I62: 604.66 | J62: =I62 -> 604.66 | K62: =J62 -> 604.66 | L62: =K62 -> 604.66 | M62: =L62 -> 604.66 | N62: =M62 -> 604.66 | O62: =N62 -> 604.66 | P62: =O62 -> 604.66
B63: (e) other financial liabilities | C63: 269.2 | D63: 311.91 | E63: 356.01 | F63: 393.96 | G63: 496.21 | H63: 497.4 | I63: 429.34 | J63: =I63 -> 429.34 | K63: =J63 -> 429.34 | L63: =K63 -> 429.34 | M63: =L63 -> 429.34 | N63: =M63 -> 429.34 | O63: =N63 -> 429.34 | P63: =O63 -> 429.34
B64: (f) short term borrowings | C64: 76.1 | D64: 747.99 | E64: 1339.42 | F64: 1758.55 | G64: 1428.71 | H64: 1136.49 | I64: 511.83 | J64: ='Debt Schedule'!J44 -> 870.111 | K64: ='Debt Schedule'!K44 -> 1479.1887 | L64: ='Debt Schedule'!L44 -> 2514.6208 | M64: ='Debt Schedule'!M44 -> 4274.8553 | N64: ='Debt Schedule'!N44 -> 7267.2541 | O64: ='Debt Schedule'!O44 -> 12354.332 | P64: ='Debt Schedule'!P44 -> 21002.364
B65: (g) government grants | C65: 0.71
B66: (f)current tax liabilities net | C66: 73.16 | D66: 47.78 | E66: 76.08 | F66: 74.55 | G66: 68.44 | H66: 92.93 | I66: 123.21 | J66: =I66 -> 123.21 | K66: =J66 -> 123.21 | L66: =K66 -> 123.21 | M66: =L66 -> 123.21 | N66: =M66 -> 123.21 | O66: =N66 -> 123.21 | P66: =O66 -> 123.21
B67: Total current liabilities | C67: =SUM(C57:C66) -> 1851.41 | D67: =SUM(D57:D66) -> 2578.46 | E67: =SUM(E58:E66) -> 3614.27 | F67: =SUM(F57:F66) -> 4147.14 | G67: =SUM(G57:G66) -> 4134.4 | H67: =SUM(H57:H66) -> 4084.41 | I67: =SUM(I57:I66) -> 3618.26 | J67: =SUM(J58:J66) -> 4089.7708 | K67: =SUM(K58:K66) -> 5014.5856 | L67: =SUM(L58:L66) -> 5889.9864 | M67: =SUM(M58:M66) -> 8403.3325 | N67: =SUM(N58:N66) -> 11454.345 | O67: =SUM(O58:O66) -> 17076.235 | P67: =SUM(P58:P66) -> 25803.937
B69: Total equity and liabilities | C69: =SUM(C44+C54+C67) -> 6241.82 | D69: =SUM(D44+D54+D67) -> 7842.23 | E69: =SUM(E44+E54+E67) -> 8008.78 | F69: =SUM(F44+F54+F67) -> 7527.41 | G69: =SUM(G44+G54+G67) -> 9352.72 | H69: =SUM(H44+H54+H67) -> 9073.56 | I69: =SUM(I44+I54+I67) -> 8838.55 | J69: =SUM(J44+J54+J67) -> 10677.767 | ... P69: =SUM(P44+P54+P67) -> 55237.737
C71: =C36-C69 -> 0 | D71: =D36-D69 -> 0 | E71: =E36-E69 -> 0 | F71: =F36-F69 -> 0 | G71: =G36-G69 -> 0 | H71: =H36-H69 -> 0 | I71: =I36-I69 -> 0 | J71: =J36-J69 -> 0.0018937527 | ... P71: =P36-P69 -> -0.00013423826

Sheet Income Statement
B1: Britannia Industries Limited
B2: INCOME STATEMENTS
B3: (in INR Crores )
B5: Particulars | C5: 2019 | D5: 2020 | E5: 2021 | F5: 2022 | G5: 2023 | H5: 2024 | I5: 2025 | J5: 2026 | K5: 2027 | L5: 2028 | M5: 2029 | N5: 2030 | O5: 2031 | P5: 2032
C6: Actual | D6: Actual | E6: Actual | F6: Actual | G6: Actual | H6: Actual | I6: Actual | J6: Forecast | K6: Forecast | L6: Forecast | M6: Forecast | N6: Forecast | O6: Forecast | P6: Forecast
A7: I | B7: Revenue from operations: | D7: =D8/C8-1 -> 0.04287891 | E7: =E8/D8-1 -> 0.12574723 | F7: =F8/E8-1 -> 0.08240524 | G7: =G8/F8-1 -> 0.14630895 | H7: =H8/G8-1 -> 0.035115015 | I7: =I8/H8-1 -> 0.059760513 | J7: =J8/I8-1 -> 0.086167566 | K7: =K8/J8-1 -> 0.08466778 | ... P7: =P8/O8-1 -> 0.13635812
B8: Sales of goods / Income from operations | C8: 10973.46 | D8: 11443.99 | E8: 12883.04 | F8: 13944.67 | G8: 15984.9 | H8: 16546.21 | I8: 17535.02 | J8: ='Revenue Schedule'!J11 -> 19045.97 | K8: ='Revenue Schedule'!K11 -> 20658.55 | L8: ='Revenue Schedule'!L11 -> 22582.57 | M8: ='Revenue Schedule'!M11 -> 24896.1 | N8: ='Revenue Schedule'!N11 -> 27701.71 | O8: ='Revenue Schedule'!O11 -> 31135.66 | P8: ='Revenue Schedule'!P11 -> 35381.26
B9: Other operating revenues | C9: 81.21 | D9: 155.56 | E9: 253.1 | F9: 191.59 | G9: 315.65 | H9: 223.06 | I9: 407.65 | J9: ='Revenue Schedule'!J12 -> 277.75725 | K9: ='Revenue Schedule'!K12 -> 301.27104 | L9: ='Revenue Schedule'!L12 -> 329.33077 | M9: ='Revenue Schedule'!M12 -> 363.07476 | N9: ='Revenue Schedule'!N12 -> 403.98653 | O9: ='Revenue Schedule'!O12 -> 454.07058 | P9: ='Revenue Schedule'!P12 -> 515.98405
B10: Total operating revenue | C10: =SUM(C8:C9) -> 11054.67 | D10: =SUM(D8:D9) -> 11599.55 | E10: =SUM(E8:E9) -> 13136.14 | F10: =SUM(F8:F9) -> 14136.26 | G10: =SUM(G8:G9) -> 16300.55 | H10: =SUM(H8:H9) -> 16769.27 | I10: =SUM(I8:I9) -> 17942.67 | J10: =SUM(J8:J9) -> 19323.727 | ... P10: =SUM(P8:P9) -> 35897.244
A11: II | B11: Other income | C11: 206.45 | D11: 279.4 | E11: 312.87 | F11: 222.83 | G11: 215.86 | H11: 214.18 | I11: 227.09 | J11: ='Other Schedule'!J13 -> 217.3739 | K11: ='Other Schedule'!K13 -> 573.46707 | L11: ='Other Schedule'!L13 -> 1088.58 | M11: ='Other Schedule'!M13 -> 1846.3069 | N11: ='Other Schedule'!N13 -> 2840.0587 | O11: ='Other Schedule'!O13 -> 4267.4362 | P11: ='Other Schedule'!P13 -> 6506.7114
A12: III | B12: Total income (I+II) | C12: =SUM(C10:C11) -> 11261.12 | D12: =SUM(D10:D11) -> 11878.95 | E12: =SUM(E10:E11) -> 13449.01 | F12: =SUM(F10:F11) -> 14359.09 | G12: =SUM(G10:G11) -> 16516.41 | H12: =SUM(H10:H11) -> 16983.45 | I12: =SUM(I10:I11) -> 18169.76 | J12: =SUM(J10:J11) -> 19541.101 | ... P12: =SUM(P10:P11) -> 42403.955
A13: IV | B13: Expenses :
B14: Cost of material consumed | C14: 5513.01 | D14: 5901.16 | E14: 6502.33 | F14: 7473.97 | G14: 8326.7 | H14: 8546.89 | I14: 9859.45 | J14: ='Cost Schedule '!J10 -> 9791.2203 | K14: ='Cost Schedule '!K10 -> 10952.213 | L14: ='Cost Schedule '!L10 -> 11373.628 | M14: ='Cost Schedule '!M10 -> 12978.79 | N14: ='Cost Schedule '!N10 -> 15175.712 | O14: ='Cost Schedule '!O10 -> 16781.81 | P14: ='Cost Schedule '!P10 -> 18444.894
B15: Purchase of stock in trade | C15: 1103.63 | D15: 973.74 | E15: 1160.89 | F15: 1361.59 | G15: 1337.13 | H15: 941.48 | I15: 809.35 | J15: ='Cost Schedule '!J11 -> 1495.8295 | K15: ='Cost Schedule '!K11 -> 1673.1972 | L15: ='Cost Schedule '!L11 -> 1737.5779 | M15: ='Cost Schedule '!M11 -> 1982.8026 | N15: ='Cost Schedule '!N11 -> 2318.432 | O15: ='Cost Schedule '!O11 -> 2563.7996 | P15: ='Cost Schedule '!P11 -> 2817.8731
B16: Changes in inventories of finished goods, work in progress and stock in trade | C16: -55.18 | D16: 52.57 | E16: -37.12 | F16: -75.26 | G16: -72.53 | H16: 3.66 | I16: -64.75 | J16: ='Cost Schedule '!J12 -> -44.268038 | K16: ='Cost Schedule '!K12 -> -49.517113 | L16: ='Cost Schedule '!L12 -> -51.422415 | M16: ='Cost Schedule '!M12 -> -58.67967 | N16: ='Cost Schedule '!N12 -> -68.612388 | O16: ='Cost Schedule '!O12 -> -75.873873 | P16: ='Cost Schedule '!P12 -> -83.393003
A17: V | B17: Cost of goods sold | C17: =SUM(C14:C16) -> 6561.46 | D17: =SUM(D14:D16) -> 6927.47 | E17: =SUM(E14:E16) -> 7626.1 | F17: =SUM(F14:F16) -> 8760.3 | G17: =SUM(G14:G16) -> 9591.3 | H17: =SUM(H14:H16) -> 9492.03 | I17: =SUM(I14:I16) -> 10604.05 | J17: =SUM(J14:J16) -> 11242.782 | ... P17: =SUM(P14:P16) -> 21179.374
B18: Employee benefits expense | C18: 441.82 | D18: 486.69 | E18: 527.38 | F18: 542.26 | G18: 658.38 | H18: 708.7 | I18: 704.59 | J18: ='Cost Schedule '!J24 -> 774.30342 | K18: ='Cost Schedule '!K24 -> 839.86184 | L18: ='Cost Schedule '!L24 -> 918.08185 | M18: ='Cost Schedule '!M24 -> 1012.1373 | N18: ='Cost Schedule '!N24 -> 1126.1977 | O18: ='Cost Schedule '!O24 -> 1265.8032 | P18: ='Cost Schedule '!P24 -> 1438.4057
B19: Finance cost | C19: 9.09 | D19: 76.9 | E19: 110.9 | F19: 144.29 | G19: 169.1 | H19: 164 | I19: 138.8 | J19: ='Debt Schedule'!J30 -> 124.53595 | K19: ='Debt Schedule'!K30 -> 187.7497 | L19: ='Debt Schedule'!L30 -> 279.95303 | M19: ='Debt Schedule'!M30 -> 420.59917 | N19: ='Debt Schedule'!N30 -> 642.57453 | O19: ='Debt Schedule'!O30 -> 1001.5613 | P19: ='Debt Schedule'!P30 -> 1591.9432
B20: Depreciation and amortisation expense | C20: 161.88 | D20: 184.81 | E20: 197.85 | F20: 200.54 | G20: 225.91 | H20: 300.46 | I20: 313.34 | J20: ='Asset Schedule'!J27 -> -281.33107 | K20: ='Asset Schedule'!K27 -> -273.68575 | L20: ='Asset Schedule'!L27 -> -271.10684 | M20: ='Asset Schedule'!M27 -> -274.63999 | N20: ='Asset Schedule'!N27 -> -285.11669 | O20: ='Asset Schedule'!O27 -> -302.69535 | P20: ='Asset Schedule'!P27 -> -328.79864
B21: Other expenses | C21: 2317.97 | D21: 2342.21 | E21: 2473.37 | F21: 2632.19 | G21: 3219.96 | H21: 3398.7 | I21: 3446.88 | J21: ='Cost Schedule '!J28 -> 3760.9658 | K21: ='Cost Schedule '!K28 -> 4079.3978 | L21: ='Cost Schedule '!L28 -> 4459.3299 | M21: ='Cost Schedule '!M28 -> 4916.1785 | N21: ='Cost Schedule '!N28 -> 5470.1954 | O21: ='Cost Schedule '!O28 -> 6148.2909 | P21: ='Cost Schedule '!P28 -> 6986.6598
A22: VI | B22: Total expenses | C22: =SUM(C17:C21) -> 9492.22 | D22: =SUM(D17:D21) -> 10018.08 | E22: =SUM(E17:E21) -> 10935.6 | F22: =SUM(F17:F21) -> 12279.58 | G22: =SUM(G17:G21) -> 13864.65 | H22: =SUM(H17:H21) -> 14063.89 | I22: =SUM(I17:I21) -> 15207.66 | J22: =SUM(J17:J21) -> 15621.256 | ... P22: =SUM(P17:P21) -> 30867.584
A23: VII | B23: Profit before share of profits/(loss) of associates (III-VI) | C23: =C12-C22 -> 1768.9 | D23: =D12-D22 -> 1860.87 | E23: =E12-E22 -> 2513.41 | F23: =F12-F22 -> 2079.51 | G23: =G12-G22 -> 2651.76 | H23: =H12-H22 -> 2919.56 | I23: =I12-I22 -> 2962.1 | J23: =J12-J22 -> 3919.8453 | ... P23: =P12-P22 -> 11536.372
B24: Share of profits/(loss) of associates | C24: -0.97 | D24: 0.44 | E24: 0.81 | F24: -0.2 | G24: 5.41 | H24: -3.19 | I24: -10.74
A25: VIII | B25: Profit before exceptional items and tax | C25: =SUM(C23:C24) -> 1767.93 | D25: =SUM(D23:D24) -> 1861.31 | E25: =SUM(E23:E24) -> 2514.22 | F25: =SUM(F23:F24) -> 2079.31 | G25: =SUM(G23:G24) -> 2657.17 | H25: =SUM(H23:H24) -> 2916.37 | I25: =SUM(I23:I24) -> 2951.36 | J25: =SUM(J23:J24) -> 3919.8453 | ... P25: =SUM(P23:P24) -> 11536.372
A26: IX | B26: Exceptional Items | C26: 0 | D26: 17.01 | E26: 0.61 | F26: 0.98 | G26: -375.6 | H26: 2.9 | I26: 24.79
A27: X | B27: Profit before tax (VIII-IX) | C27: =C25-C26 -> 1767.93 | D27: =D25-D26 -> 1844.3 | E27: =E25-E26 -> 2513.61 | F27: =F25-F26 -> 2078.33 | G27: =G25-G26 -> 3032.77 | H27: =H25-H26 -> 2913.47 | I27: =I25-I26 -> 2926.57 | J27: =J25-J26 -> 3919.8453 | ... P27: =P25-P26 -> 11536.372
A28: XI | B28: Tax Expense :
B29: (i) Current Tax | C29: 599.78 | D29: 447.69 | E29: 657.12 | F29: 612.24 | G29: 720.97 | H29: 765.69 | I29: 741.68 | J29: ='Cost Schedule '!J36 -> 1026.6887 | K29: ='Cost Schedule '!K36 -> 1080.1799 | L29: ='Cost Schedule '!L36 -> 1454.8228 | M29: ='Cost Schedule '!M36 -> 1605.1271 | N29: ='Cost Schedule '!N36 -> 1719.869 | O29: ='Cost Schedule '!O36 -> 2219.6396 | P29: ='Cost Schedule '!P36 -> 3021.6148
B30: (ii) Deffered Tax | C30: 12.69 | D30: 3.01 | E30: 5.9 | F30: -49.89 | G30: -4.52 | H30: 13.56 | I30: 7.03 | J30: ='Cost Schedule '!J37 -> -17.220281 | K30: ='Cost Schedule '!K37 -> -18.117469 | L30: ='Cost Schedule '!L37 -> -24.401219 | M30: ='Cost Schedule '!M37 -> -26.92222 | N30: ='Cost Schedule '!N37 -> -28.846745 | O30: ='Cost Schedule '!O37 -> -37.229217 | P30: ='Cost Schedule '!P37 -> -50.680459
B31: Total tax expense | C31: =SUM(C29:C30) -> 612.47 | D31: =SUM(D29:D30) -> 450.7 | E31: =SUM(E29:E30) -> 663.02 | F31: =SUM(F29:F30) -> 562.35 | G31: =SUM(G29:G30) -> 716.45 | H31: =SUM(H29:H30) -> 779.25 | I31: =SUM(I29:I30) -> 748.71 | J31: =SUM(J29:J30) -> 1009.4684 | ... P31: =SUM(P29:P30) -> 2970.9343
A32: XII | B32: Profit for the year (X-XI) | C32: =C27-C31 -> 1155.46 | D32: =D27-D31 -> 1393.6 | E32: =E27-E31 -> 1850.59 | F32: =F27-F31 -> 1515.98 | G32: =G27-G31 -> 2316.32 | H32: =H27-H31 -> 2134.22 | I32: =I27-I31 -> 2177.86 | J32: =J27-J31 -> 2910.3768 | ... P32: =P27-P31 -> 8565.4372
A33: XIII | B33: Other comprehensive income :
B34: Remeasurements of the net defined benefit (liability)/asset | C34: -4.09 | D34: -6.5 | E34: 3.5 | F34: 0.17 | G34: -0.16 | H34: -2.39 | I34: -1.92
B35: Income-tax relating to items not to be reclassified subsequently to statement of profit or loss | C35: 1.43 | D35: 1.57 | E35: -0.92 | F35: -0.05 | G35: 0.04 | H35: 0.64 | I35: 0.5
B36: Foreign currency translation reserve | C36: 6.5 | D36: 10.05 | E36: -4.08 | F36: 6.17 | G36: 15.43 | H36: 2.87 | I36: 7.68
B37: Other comprehensive income/(loss),net of tax | C37: =SUM(C34:C36) -> 3.84 | D37: =SUM(D34:D36) -> 5.12 | E37: =SUM(E34:E36) -> -1.5 | F37: =SUM(F34:F36) -> 6.29 | G37: =SUM(G34:G36) -> 15.31 | H37: =SUM(H34:H36) -> 1.12 | I37: =SUM(I34:I36) -> 6.26
A38: XIV | B38: Total comprehensive income for the year ( XII+XIII) | C38: =SUM(C32+C37) -> 1159.3 | D38: =SUM(D32+D37) -> 1398.72 | E38: =SUM(E32+E37) -> 1849.09 | F38: =SUM(F32+F37) -> 1522.27 | G38: =SUM(G32+G37) -> 2331.63 | H38: =SUM(H32+H37) -> 2135.34 | I38: =SUM(I32+I37) -> 2184.12 | J38: =SUM(J32+J37) -> 2910.3768 | ... P38: =SUM(P32+P37) -> 8565.4372
B39: Profit attributable to :
B40: Owners of the company | C40: 1159.12 | D40: 1402.63 | E40: 1863.9 | F40: 1524.82 | G40: 2321.77 | H40: 2139.81 | I40: 2178.73
B41: Non-controlling interests | C41: -3.66 | D41: -9.03 | E41: -13.31 | F41: -8.84 | G41: -5.45 | H41: -5.59 | I41: -0.87
B42: Profit for the year | C42: =SUM(C40:C41) -> 1155.46 | D42: =SUM(D40:D41) -> 1393.6 | E42: =SUM(E40:E41) -> 1850.59 | F42: =SUM(F40:F41) -> 1515.98 | G42: =SUM(G40:G41) -> 2316.32 | H42: =SUM(H40:H41) -> 2134.22 | I42: =SUM(I40:I41) -> 2177.86 | J42: =SUM(J40:J41) -> 0 | ... P42: =SUM(P40:P41) -> 0
B43: Other comprehensive income attributable to:
B44: Owners of the company | C44: 3.84 | D44: 5.12 | E44: -1.5 | F44: 6.29 | G44: 15.38 | H44: 1.69 | I44: 5.85
B45: Non-controlling interests | C45: 0 | D45: 0 | E45: 0 | F45: 0 | G45: -0.07 | H45: -0.57 | I45: 0.41
B46: Total comprensive income attributable to:
B47: Owners of the company | C47: 1162.96 | D47: 1407.75 | E47: 1862.4 | F47: 1531.11 | G47: 2337.15 | H47: 2141.5 | I47: 2184.58
B48: Non-controlling interests | C48: -3.66 | D48: -9.03 | E48: -13.31 | F48: -8.84 | G48: -5.52 | H48: -6.16 | I48: -0.46
B49: Total comprehensive income for the year | C49: =SUM(C47:C48) -> 1159.3 | D49: =SUM(D47:D48) -> 1398.72 | E49: =SUM(E47:E48) -> 1849.09 | F49: =SUM(F47:F48) -> 1522.27 | G49: =SUM(G47:G48) -> 2331.63 | H49: =SUM(H47:H48) -> 2135.34 | I49: =SUM(I47:I48) -> 2184.12 | J49: =SUM(J47:J48) -> 0 | ... P49: =SUM(P47:P48) -> 0
B51: Earnings per share (face value of ' 1 each)
B52: Basic [in '] | C52: 48.25 | D52: 58.35 | E52: 77.43 | F52: 63.31 | G52: 96.39 | H52: 88.84 | I52: 90.45
B53: Diluted [in '] | C53: 48.21 | D53: 58.34 | E53: 77.4 | F53: 63.31 | G53: 96.39 | H53: 88.84 | I53: 90.45

Sheet CFS
B1: Britannia Industries Limited
B2: CASH FLOW STATEMENT
B4: Particulars | C4: 2019 | D4: 2020 | E4: 2021 | F4: 2022 | G4: 2023 | H4: 2024 | I4: 2025 | J4: 2026 | K4: 2027 | L4: 2028 | M4: 2029 | N4: 2030 | O4: 2031 | P4: 2032
C5: Actual | D5: Actual | E5: Actual | F5: Actual | G5: Actual | H5: Actual | I5: Actual | J5: Forecast | K5: Forecast | L5: Forecast | M5: Forecast | N5: Forecast | O5: Forecast | P5: Forecast
A6: I | B6: Cash flow from operating activities
B7: Profit before tax and share of profits / (loss) of associates and after exceptional item | C7: ='Income Statement'!C23 -> 1768.9 | D7: ='Income Statement'!D27 -> 1844.3 | E7: ='Income Statement'!E27 -> 2513.61 | F7: 2078.53 | G7: 3027.36 | H7: 2916.66 | I7: 2937.31 | J7: ='Income Statement'!J27 -> 3919.8453 | K7: ='Income Statement'!K27 -> 4124.0719 | L7: ='Income Statement'!L27 -> 5554.4393 | M7: ='Income Statement'!M27 -> 6128.2936 | N7: ='Income Statement'!N27 -> 6566.3725 | O7: ='Income Statement'!O27 -> 8474.471 | P7: ='Income Statement'!P27 -> 11536.372
B8: Adjustments for
B9: Depreciation and amortisation expense | C9: 161.88 | D9: 184.81 | E9: 197.85 | F9: 200.54 | G9: 225.91 | H9: 300.46 | I9: 313.34 | J9: =-'Asset Schedule'!J10 -> 281.33107 | K9: =-'Asset Schedule'!K10 -> 273.68575 | L9: =-'Asset Schedule'!L10 -> 271.10684 | M9: =-'Asset Schedule'!M10 -> 274.63999 | N9: =-'Asset Schedule'!N10 -> 285.11669 | O9: =-'Asset Schedule'!O10 -> 302.69535 | P9: =-'Asset Schedule'!P10 -> 328.79864
B10: Share based payment expense | C10: 16.12 | D10: 21.58 | E10: 18.94 | F10: 4.78 | G10: 0 | H10: 0 | I10: 0
B11: Net gain on financial asset measured at fair value through Statement of Profit and Loss | C11: -63.85 | D11: -89.88 | E11: -65.47 | F11: -28.91 | G11: -42.08 | H11: -25.17 | I11: -81.35
B12: Profit on sale of property, plant and equipment | C12: -0.97 | D12: -0.11 | E12: -0.33 | F12: -0.95 | G12: -0.83 | H12: -0.45 | I12: -1.24
B13: Exceptional items-Gain on sale of investments (including fair valuation gain) | C13: 0 | D13: 0 | E13: 0 | F13: 0 | G13: -375.6 | H13: 0 | I13: 0
B14: Interest income from financial assets carried at amortised cost | C14: -136.77 | D14: -176.77 | E14: -234.66 | F14: -184.6 | G14: -163.15 | H14: -178.75 | I14: -132.8 | J14: =-('Other Schedule'!J18) -> -209.832 | K14: =-('Other Schedule'!K18) -> -573.46561 | L14: =-('Other Schedule'!L18) -> -1088.5837 | M14: =-('Other Schedule'!M18) -> -1846.3108 | N14: =-('Other Schedule'!N18) -> -2840.0584 | O14: =-('Other Schedule'!O18) -> -4267.4366 | P14: =-('Other Schedule'!P18) -> -6506.7073
B15: Bad debts | C15: 0 | D15: 0 | E15: 0 | F15: 0 | G15: 5.59 | H15: 0 | I15: 0
B16: Finance costs | C16: 9.09 | D16: 76.9 | E16: 110.9 | F16: 144.29 | G16: 169.1 | H16: 164 | I16: 138.8 | J16: ='Debt Schedule'!J30 -> 124.53595 | K16: ='Debt Schedule'!K30 -> 187.7497 | L16: ='Debt Schedule'!L30 -> 279.95303 | M16: ='Debt Schedule'!M30 -> 420.59917 | N16: ='Debt Schedule'!N30 -> 642.57453 | O16: ='Debt Schedule'!O30 -> 1001.5613 | P16: ='Debt Schedule'!P30 -> 1591.9432
B17: Changes in working capital
B18: Inventories | C18: -127.21 | D18: 42.99 | E18: -351.44 | F18: -274.76 | G18: 177.15 | H18: 12.6 | I18: -54.33 | J18: =-('Balance Sheet'!J24-'Balance Sheet'!I24) -> -291.16933 | K18: =-('Balance Sheet'!K24-'Balance Sheet'!J24) -> -99.057526 | L18: =-('Balance Sheet'!L24-'Balance Sheet'!K24) -> -46.450389 | M18: =-('Balance Sheet'!M24-'Balance Sheet'!L24) -> -357.64923 | N18: =-('Balance Sheet'!N24-'Balance Sheet'!M24) -> -220.03558 | O18: =-('Balance Sheet'!O24-'Balance Sheet'!N24) -> -219.14565 | P18: =-('Balance Sheet'!P24-'Balance Sheet'!O24) -> -313.94554
B19: Trade receivables | C19: -86.67 | D19: 78.85 | E19: 61.4 | F19: -72.21 | G19: 1.29 | H19: -63.65 | I19: -53.44 | J19: =-('Balance Sheet'!J27-'Balance Sheet'!I27) -> 19.930892 | K19: =-('Balance Sheet'!K27-'Balance Sheet'!J27) -> -94.208863 | L19: =-('Balance Sheet'!L27-'Balance Sheet'!K27) -> 5.5852626 | M19: =-('Balance Sheet'!M27-'Balance Sheet'!L27) -> -112.15052 | N19: =-('Balance Sheet'!N27-'Balance Sheet'!M27) -> -17.080377 | O19: =-('Balance Sheet'!O27-'Balance Sheet'!N27) -> -141.09331 | P19: =-('Balance Sheet'!P27-'Balance Sheet'!O27) -> -54.465998
B20: Loans receivable, other financial assets, other bank balances and other assets | C20: 10.9 | D20: -23.66 | E20: -170.82 | F20: -44.29 | G20: -64.82 | H20: -24.52 | I20: -106.58
B21: Accounts payables, other financial liabilities, other liabilities and provisions | C21: 200.49 | D21: 29.21 | E21: 404.71 | F21: 64.01 | G21: 292.04 | H21: 236.67 | I21: 210.15 | J21: ='Working Capital Schedule'!J37-'Working Capital Schedule'!I37 -> 113.22976 | K21: ='Working Capital Schedule'!K37-'Working Capital Schedule'!J37 -> 315.73716 | L21: ='Working Capital Schedule'!L37-'Working Capital Schedule'!K37 -> -160.03132 | M21: ='Working Capital Schedule'!M37-'Working Capital Schedule'!L37 -> 753.11153 | N21: ='Working Capital Schedule'!N37-'Working Capital Schedule'!M37 -> 58.613916 | O21: ='Working Capital Schedule'!O37-'Working Capital Schedule'!N37 -> 534.81192 | P21: ='Working Capital Schedule'!P37-'Working Capital Schedule'!O37 -> 79.669368
B22: Cash generated from operating activities | C22: =SUM(C7:C21) -> 1751.91 | D22: =SUM(D7:D21) -> 1988.22 | E22: =SUM(E7:E21) -> 2484.69 | F22: =SUM(F7:F21) -> 1886.43 | G22: =SUM(G7:G21) -> 3251.96 | H22: =SUM(H7:H21) -> 3337.85 | I22: =SUM(I7:I21) -> 3169.86 | J22: =SUM(J7:J21) -> 3957.8716 | ... P22: =SUM(P7:P21) -> 6661.6638
B23: Income-tax paid, net of refund | C23: -596.13 | D23: -503.25 | E23: -632.81 | F23: -586.91 | G23: -725.75 | H23: -764.87 | I23: -689.21 | J23: =-('Cost Schedule '!J38) -> -1009.4684 | K23: =-('Cost Schedule '!K38) -> -1062.0624 | L23: =-('Cost Schedule '!L38) -> -1430.4215 | M23: =-('Cost Schedule '!M38) -> -1578.2049 | N23: =-('Cost Schedule '!N38) -> -1691.0223 | O23: =-('Cost Schedule '!O38) -> -2182.4104 | P23: =-('Cost Schedule '!P38) -> -2970.9343
B25: Net cash generated from operating activities | C25: =SUM(C22:C23) -> 1155.78 | D25: =SUM(D22:D23) -> 1484.97 | E25: =SUM(E22:E23) -> 1851.88 | F25: =SUM(F22:F23) -> 1299.52 | G25: =SUM(G22:G23) -> 2526.21 | H25: =SUM(H22:H23) -> 2572.98 | I25: =SUM(I22:I23) -> 2480.65 | J25: =SUM(J22:J23) -> 2948.4032 | ... P25: =SUM(P22:P23) -> 3690.7295
A27: II | B27: Cash flow from investing activities
B28: Acquisition of property, plant and equipment and other intangible assets | C28: -401.21 | D28: -244.17 | E28: -242.07 | F28: -550.18 | G28: -711.46 | H28: -552.87 | I28: -374.85 | J28: =-('Asset Schedule'!J8) -> -195.42542 | K28: =-('Asset Schedule'!K8) -> -229.78572 | L28: =-('Asset Schedule'!L8) -> -275.87598 | M28: =-('Asset Schedule'!M8) -> -338.8667 | N28: =-('Asset Schedule'!N8) -> -417.5453 | O28: =-('Asset Schedule'!O8) -> -505.54575 | P28: =-('Asset Schedule'!P8) -> -616.84705
B29: Proceeds from sale of non-current investments | C29: 0 | D29: 0 | E29: 0 | F29: 191.78 | G29: 443.27 | H29: 294.22 | I29: 572.16
B30: Proceeds from sale of property, plant and equipment | C30: 1.82 | D30: 0.73 | E30: 2.17 | F30: 3.16 | G30: 78.43 | H30: 64.52 | I30: 4.58 | J30: =-'Asset Schedule'!J22 -> 31.493445 | K30: =-'Asset Schedule'!K22 -> 30.200782 | L30: =-'Asset Schedule'!L22 -> 29.384869 | M30: =-'Asset Schedule'!M22 -> 29.113829 | N30: =-'Asset Schedule'!N22 -> 29.500452 | O30: =-'Asset Schedule'!O22 -> 30.633778 | P30: =-'Asset Schedule'!P22 -> 32.530029
B31: Purchase of investments, net | C31: -334.12 | D31: -1326.63 | E31: 0 | F31: -20.68 | G31: -400.82 | H31: -190.9 | I31: -945.05
B32: Sale of current investments, net | C32: 0 | D32: 0 | E32: 178.82 | F32: 876.87 | G32: -1067.32 | H32: 476.87 | I32: 347.31
B33: Investment in joint venture | C33: 0 | D33: 0 | E33: 0 | F33: 0 | G33: -214.91 | H33: 0 | I33: 0
B34: Proceeds from sale of equity shares in subsidiary (net of cash and cash equivalent) | C34: 0 | D34: 0 | E34: 0 | F34: 0 | G34: 261.8 | H34: 0 | I34: 0
B35: Inter-corporate deposits placed | C35: -874.3 | D35: -1293.41 | E35: =-1202.5 -> -1202.5 | F35: -740 | G35: -850 | H35: -610 | I35: -75
B36: Inter-corporate deposits redeemed | C36: 635.4 | D36: 1204.2 | E36: 1491.41 | F36: 941.5 | G36: 938 | H36: 860 | I36: 460
B37: Changes in other bank balances | C37: 0 | D37: 0 | E37: 0 | F37: 1.69 | G37: -28.69 | H37: -27.95 | I37: -56.15
B38: Consideration paid under business combination | C38: 0 | D38: 0 | E38: 0 | F38: 0 | G38: -1.45 | H38: 0 | I38: 0
B39: Derecognition of net asset on loss of control [refer note 58(b)] | C39: 0 | D39: 0 | E39: 0 | F39: 0 | G39: -138.59 | H39: 0 | I39: 0
B40: Interest received | C40: 116.88 | D40: 127.62 | E40: 233.43 | F40: 206.75 | G40: 174.68 | H40: 170.26 | I40: 151.36 | J40: ='Other Schedule'!J13 -> 217.3739 | K40: ='Other Schedule'!K13 -> 573.46707 | L40: ='Other Schedule'!L13 -> 1088.58 | M40: ='Other Schedule'!M13 -> 1846.3069 | N40: ='Other Schedule'!N13 -> 2840.0587 | O40: ='Other Schedule'!O13 -> 4267.4362 | P40: ='Other Schedule'!P13 -> 6506.7114
B41: Net cash used in investing activities | C41: =SUM(C28:C40) -> -855.53 | D41: =SUM(D28:D40) -> -1531.66 | E41: =SUM(E28:E40) -> 461.26 | F41: =SUM(F28:F40) -> 910.89 | G41: =SUM(G28:G40) -> -1517.06 | H41: =SUM(H28:H40) -> 484.15 | I41: =SUM(I28:I40) -> 84.36 | J41: =SUM(J28:J40) -> 53.441927 | ... P41: =SUM(P28:P40) -> 5922.3944
A43: III | B43: Cash flow from financing activities
B44: Proceeds from share allotment | C44: 29.79 | D44: 23.97 | E44: 103.15 | F44: 0 | G44: 0 | H44: 0 | I44: 0
B45: Principal payment of lease liabilities | C45: 0 | D45: -2.03 | E45: -2.55 | F45: -1.55 | G45: -2.76 | H45: -1.95 | I45: -3.58
B46: Proceeds from lease liablilities | G46: 2.69 | H46: 0 | I46: 0
B47: Interest paid on lease liabilities | C47: 0 | D47: -0.45 | E47: -1.04 | F47: -0.65 | G47: -0.63 | H47: -0.62 | I47: -0.89
B48: Interest paid | C48: -9.38 | D48: -35.54 | E48: -101.3 | F48: -118.61 | G48: -195.66 | H48: -164.28 | I48: -170.62 | J48: =-('Debt Schedule'!J30) -> -124.53595 | K48: =-('Debt Schedule'!K30) -> -187.7497 | L48: =-('Debt Schedule'!L30) -> -279.95303 | M48: =-('Debt Schedule'!M30) -> -420.59917 | N48: =-('Debt Schedule'!N30) -> -642.57453 | O48: =-('Debt Schedule'!O30) -> -1001.5613 | P48: =-('Debt Schedule'!P30) -> -1591.9432
B49: Issue of bonus debentures | C49: 0 | D49: 720.95 | E49: 0 | F49: 698.52 | G49: 0 | H49: 0 | I49: 0 | J49: ='Debt Schedule'!J11 -> 307.98329 | K49: ='Debt Schedule'!K11 -> 334.0595 | L49: ='Debt Schedule'!L11 -> 365.17192 | M49: ='Debt Schedule'!M11 -> 402.58299 | N49: ='Debt Schedule'!N11 -> 447.9511 | O49: ='Debt Schedule'!O11 -> 503.47995 | P49: ='Debt Schedule'!P11 -> 572.13348
B50: Net proceeds from other working capital borrowing | C50: 0 | D50: 0 | E50: 0 | F50: 645.35 | G50: 299.4 | H50: 0 | I50: 0
B51: Proceeds from issue of Commercial paper | C51: 0 | D51: 0 | E51: 0 | F51: 0 | G51: 0 | H51: 0 | I51: 0
B52: Proceeds from non current borrowings | C52: 0 | D52: 0 | E52: 0 | F52: 0 | G52: 1010 | H52: 200.84 | I52: 0
B53: Repayment of non-current borrowings | C53: 0 | D53: 0 | E53: 0 | F53: 0 | G53: 0 | H53: -113.6 | I53: -148.53
B54: Repayment of term loans | C54: 0 | D54: 0 | E54: 0 | F54: -17.73 | G54: -70.23 | H54: 0 | I54: 0 | J54: ='Debt Schedule'!J12 -> -14.620945 | K54: ='Debt Schedule'!K12 -> -20.637208 | L54: ='Debt Schedule'!L12 -> -27.06486 | M54: ='Debt Schedule'!M12 -> -33.998746 | N54: ='Debt Schedule'!N12 -> -41.557656 | O54: ='Debt Schedule'!O12 -> -49.891957 | P54: ='Debt Schedule'!P12 -> -59.194121
B55: Proceeds from / (Repayment of) borrowings, net* | C55: -41.91 | D55: 640.722 | E55: 567.8 | F55: 0 | G55: 0 | H55: -1027.48 | I55: 26.26 | J55: ='Debt Schedule'!J42 -> 358.281 | K55: ='Debt Schedule'!K42 -> 609.0777 | L55: ='Debt Schedule'!L42 -> 1035.4321 | M55: ='Debt Schedule'!M42 -> 1760.2346 | N55: ='Debt Schedule'!N42 -> 2992.3987 | O55: ='Debt Schedule'!O42 -> 5087.0779 | P55: ='Debt Schedule'!P42 -> 8648.0324
B56: Contribution from non-controlling interest | C56: 23.2 | D56: 12 | E56: 14 | F56: -966.29 | G56: 9.01 | H56: 0.43 | I56: 1.56
B57: Dividends paid (including dividend distribution tax) | C57: -354.38 | D57: -432.53 | E57: -2823.75 | F57: -2484.88 | G57: -1359.24 | H57: -1732.47 | I57: -1767.54 | J57: =AVERAGE(F57:I57) -> -1836.0325 | K57: -1836.0325 | L57: -1836.0325 | M57: -1836.0325 | N57: -1836.0325 | O57: -1836.0325 | P57: -1836.0325
B58: Payment of bonus debentures (including dividend distribution tax) | C58: 0 | D58: -869.15 | E58: 0 | F58: 0 | G58: -720.95 | H58: 0 | I58: -698.52
B59: Net cash generated from / (used in) financing activities | C59: =SUM(C44:C58) -> -352.68 | D59: =SUM(D44:D58) -> 57.942 | E59: =SUM(E44:E58) -> -2243.69 | F59: =SUM(F44:F58) -> -2245.84 | G59: =SUM(G44:G58) -> -1028.37 | H59: =SUM(H44:H58) -> -2839.13 | I59: =SUM(I44:I58) -> -2761.86 | J59: =SUM(J44:J58) -> -1308.9251 | ... P59: =SUM(P44:P58) -> 5732.996
B61: Net increase (decrease) in cash and cash equivalents | C61: =SUM(C59+C41+C25) -> -52.43 | D61: =SUM(D59+D41+D25) -> 11.252 | E61: =SUM(E59+E41+E25) -> 69.45 | F61: =SUM(F59+F41+F25) -> -35.43 | G61: =SUM(G59+G41+G25) -> -19.22 | H61: =SUM(H59+H41+H25) -> 218 | I61: =SUM(I59+I41+I25) -> -196.85 | J61: =SUM(J25+J41+J59) -> 1692.92 | K61: =SUM(K25+K41+K59) -> 2345.05 | L61: =SUM(L25+L41+L59) -> 3485.24 | M61: =SUM(M25+M41+M59) -> 5091.07 | N61: =SUM(N25+N41+N59) -> 6156.68 | O61: =SUM(O25+O41+O59) -> 9999.05 | P61: =SUM(P25+P41+P59) -> 15346.12
B62: Cash and Cash Equivalents at beginning of period | C62: 3.31 | D62: 5.69 | E62: -2.44 | F62: 3.3 | G62: 10.06 | H62: 100.16 | I62: 319.45 | J62: =I64 -> 125.24 | K62: =J64 -> 1818.16 | L62: =K64 -> 4163.21 | M62: =L64 -> 7648.45 | N62: =M64 -> 12739.52 | O62: =N64 -> 18896.2 | P62: =O64 -> 28895.25
B63: Effect of exchange rate change on cash | C63: 107.84 | D63: 58.72 | E63: 75.26 | F63: 141.45 | G63: 109.32 | H63: 1.29 | I63: 2.64
B64: Cash and Cash equivalents at the end of the periods | C64: =SUM(C61:C63) -> 58.72 | D64: =SUM(D61:D63) -> 75.662 | E64: =SUM(E61:E63) -> 142.27 | F64: =SUM(F61:F63) -> 109.32 | G64: =SUM(G61:G63) -> 100.16 | H64: =SUM(H61:H63) -> 319.45 | I64: =SUM(I61:I63) -> 125.24 | J64: =SUM(J61:J62) -> 1818.16 | K64: =SUM(K61:K62) -> 4163.21 | L64: =SUM(L61:L62) -> 7648.45 | M64: =SUM(M61:M62) -> 12739.52 | N64: =SUM(N61:N62) -> 18896.2 | O64: =SUM(O61:O62) -> 28895.25 | P64: =SUM(P61:P62) -> 44241.37

Sheet RATIO ANALYSIS
B1: Britannia Industries Limited
B2: RATIO ANALYSIS
B4: Particulars | C4: 2019 | D4: 2020 | E4: 2021 | F4: 2022 | G4: 2023 | H4: 2024 | I4: 2025 | J4: 2026 | K4: 2027 | L4: 2028 | M4: 2029 | N4: 2030 | O4: 2031 | P4: 2032 | R4: TRENDS | S4: MEDIAN
C5: Actual | D5: Actual | E5: Actual | F5: Actual | G5: Actual | H5: Actual | I5: Actual | J5: Forecast | K5: Forecast | L5: Forecast | M5: Forecast | N5: Forecast | O5: Forecast | P5: Forecast
B6: GROWTH FACTORS | E6: 2021 | F6: 2022 | G6: 2023 | H6: 2024 | I6: 2025
B7: Revenue Growth (%) | C7: ='Income Statement'!C7 -> 0 | D7: ='Income Statement'!D7 -> 0.04287891 | E7: ='Income Statement'!E7 -> 0.12574723 | F7: ='Income Statement'!F7 -> 0.08240524 | G7: ='Income Statement'!G7 -> 0.14630895 | H7: ='Income Statement'!H7 -> 0.035115015 | I7: ='Income Statement'!I7 -> 0.059760513 | J7: ='Income Statement'!J7 -> 0.086167566 | ... P7: ='Income Statement'!P7 -> 0.13635812 | S7: =MEDIAN(C7:P7) -> 0.089650943
B8: Gross Profit Growth (%) | D8: 0.039808956 | E8: 0.17935481 | F8: -0.024333762 | G8: 0.24800966 | H8: 0.084657749 | I8: 0.0084345164 | J8: 0.10115328 | K8: 0.0374935 | L8: 0.17511945 | M8: 0.051171165 | N8: 0.031276057 | O8: 0.15353979 | P8: 0.1946328 | S8: =MEDIAN(C8:P8) -> 0.084657749
B9: EBITDA Growth (%) | D9: 0.086188045 | E9: 0.34014558 | F9: -0.14144191 | G9: 0.41459086 | H9: -0.01454294 | I9: 0.00023091065 | J9: 0.11375352 | K9: 0.073101789 | L9: 0.37768657 | M9: 0.12779629 | N9: 0.10353067 | O9: 0.32489339 | P9: 0.39529553 | S9: =MEDIAN(C9:P9) -> 0.11375352
B10: EBIT Growth (%) | D10: 0.090708039 | E10: 0.35440432 | F10: -0.15295301 | G10: 0.27103346 | H10: 0.089906485 | I10: 0.0031781896 | J10: 0.30879346 | K10: 0.066126401 | L10: 0.35311543 | M10: 0.12246355 | N10: 0.10078868 | O10: 0.31448218 | P10: 0.38542316 | S10: =MEDIAN(C10:P10) -> 0.12246355
B11: Pre-Tax Growth (%) | D11: ='Income Statement'!D25/'Income Statement'!C25-1 -> 0.052818833 | E11: ='Income Statement'!E25/'Income Statement'!D25-1 -> 0.35077983 | F11: ='Income Statement'!F25/'Income Statement'!E25-1 -> -0.17298009 | G11: ='Income Statement'!G25/'Income Statement'!F25-1 -> 0.2779095 | H11: ='Income Statement'!H25/'Income Statement'!G25-1 -> 0.097547391 | I11: ='Income Statement'!I25/'Income Statement'!H25-1 -> 0.011997792 | J11: ='Income Statement'!J25/'Income Statement'!I25-1 -> 0.32814881 | K11: ='Income Statement'!K25/'Income Statement'!J25-1 -> 0.052100685 | ... P11: ='Income Statement'!P25/'Income Statement'!O25-1 -> 0.36130875 | S11: =MEDIAN(C11:P11) -> 0.10331452
B14: MARGIN
B15: Gross Profit Margin (%) | C15: =('Income Statement'!C10-'Income Statement'!C17)/'Income Statement'!C10 -> 0.40645356 | D15: =('Income Statement'!D10-'Income Statement'!D17)/'Income Statement'!D10 -> 0.40278114 | E15: =('Income Statement'!E10-'Income Statement'!E17)/'Income Statement'!E10 -> 0.41945655 | F15: =('Income Statement'!F10-'Income Statement'!F17)/'Income Statement'!F10 -> 0.38029578 | G15: =('Income Statement'!G10-'Income Statement'!G17)/'Income Statement'!G10 -> 0.41159654 | H15: =('Income Statement'!H10-'Income Statement'!H17)/'Income Statement'!H10 -> 0.43396284 | I15: =('Income Statement'!I10-'Income Statement'!I17)/'Income Statement'!I10 -> 0.40900379 | J15: =('Income Statement'!J10-'Income Statement'!J17)/'Income Statement'!J10 -> 0.41818772 | ... P15: =('Income Statement'!P10-'Income Statement'!P17)/'Income Statement'!P10 -> 0.41 | S15: =MEDIAN(C15:P15) -> 0.40950189
B16: EBITDA Margin (%) | C16: =('Income Statement'!C27+'Income Statement'!C19+'Income Statement'!C20)/'Income Statement'!C10 -> 0.17539194 | D16: =('Income Statement'!D27+'Income Statement'!D19+'Income Statement'!D20)/'Income Statement'!D10 -> 0.18155963 | E16: =('Income Statement'!E27+'Income Statement'!E19+'Income Statement'!E20)/'Income Statement'!E10 -> 0.21485459 | F16: =('Income Statement'!F27+'Income Statement'!F19+'Income Statement'!F20)/'Income Statement'!F10 -> 0.1714145 | G16: =('Income Statement'!G27+'Income Statement'!G19+'Income Statement'!G20)/'Income Statement'!G10 -> 0.21028616 | H16: =('Income Statement'!H27+'Income Statement'!H19+'Income Statement'!H20)/'Income Statement'!H10 -> 0.20143572 | I16: =('Income Statement'!I27+'Income Statement'!I19+'Income Statement'!I20)/'Income Statement'!I10 -> 0.18830587 | J16: =('Income Statement'!J27+'Income Statement'!J19+'Income Statement'!J20)/'Income Statement'!J10 -> 0.19473728 | ... P16: =('Income Statement'!P27+'Income Statement'!P19+'Income Statement'!P20)/'Income Statement'!P10 -> 0.35655985 | S16: =MEDIAN(C16:P16) -> 0.20586094
B17: EBIT Margin (%) | C17: =('Income Statement'!C25+'Income Statement'!C19)/'Income Statement'!C10 -> 0.16074835 | D17: =('Income Statement'!D25+'Income Statement'!D19)/'Income Statement'!D10 -> 0.16709355 | E17: =('Income Statement'!E25+'Income Statement'!E19)/'Income Statement'!E10 -> 0.19983953 | F17: =('Income Statement'!F25+'Income Statement'!F19)/'Income Statement'!F10 -> 0.15729762 | G17: =('Income Statement'!G25+'Income Statement'!G19)/'Income Statement'!G10 -> 0.17338495 | H17: =('Income Statement'!H25+'Income Statement'!H19)/'Income Statement'!H10 -> 0.18369136 | I17: =('Income Statement'!I25+'Income Statement'!I19)/'Income Statement'!I10 -> 0.17222409 | J17: =('Income Statement'!J25+'Income Statement'!J19)/'Income Statement'!J10 -> 0.20929612 | ... P17: =('Income Statement'!P25+'Income Statement'!P19)/'Income Statement'!P10 -> 0.36571929 | S17: =MEDIAN(C17:P17) -> 0.20277898
B18: Pre-Tax Margin (%) | C18: ='Income Statement'!C25/'Income Statement'!C10 -> 0.15992608 | D18: ='Income Statement'!D25/'Income Statement'!D10 -> 0.16046398 | E18: ='Income Statement'!E25/'Income Statement'!E10 -> 0.19139717 | F18: ='Income Statement'!F25/'Income Statement'!F10 -> 0.14709053 | G18: ='Income Statement'!G25/'Income Statement'!G10 -> 0.16301106 | H18: ='Income Statement'!H25/'Income Statement'!H10 -> 0.17391157 | I18: ='Income Statement'!I25/'Income Statement'!I10 -> 0.16448834 | J18: ='Income Statement'!J25/'Income Statement'!J10 -> 0.20285141 | ... P18: ='Income Statement'!P25/'Income Statement'!P10 -> 0.32137207 | S18: =MEDIAN(C18:P18) -> 0.194079
B19: Effective Tax Rate (%) | C19: ='Income Statement'!C31/'Income Statement'!C27 -> 0.3464334 | D19: ='Income Statement'!D31/'Income Statement'!D27 -> 0.24437456 | E19: ='Income Statement'!E31/'Income Statement'!E27 -> 0.26377203 | F19: ='Income Statement'!F31/'Income Statement'!F27 -> 0.27057782 | G19: ='Income Statement'!G31/'Income Statement'!G27 -> 0.23623618 | H19: ='Income Statement'!H31/'Income Statement'!H27 -> 0.26746457 | I19: ='Income Statement'!I31/'Income Statement'!I27 -> 0.25583191 | J19: ='Income Statement'!J31/'Income Statement'!J27 -> 0.25752762 | ... P19: ='Income Statement'!P31/'Income Statement'!P27 -> 0.25752762 | S19: =MEDIAN(C19:P19) -> 0.25752762
B21: LIQUIDITY RATIOS
B22: Current Ratio | C22: ='Balance Sheet'!C34/'Balance Sheet'!C67 -> 1.9046781 | D22: ='Balance Sheet'!D34/'Balance Sheet'!D67 -> 1.4252577 | E22: ='Balance Sheet'!E34/'Balance Sheet'!E67 -> 1.2228417 | F22: ='Balance Sheet'!F34/'Balance Sheet'!F67 -> 0.96025213 | G22: ='Balance Sheet'!G34/'Balance Sheet'!G67 -> 1.1479852 | H22: ='Balance Sheet'!H34/'Balance Sheet'!H67 -> 1.1871139 | I22: ='Balance Sheet'!I34/'Balance Sheet'!I67 -> 1.081647 | J22: ='Balance Sheet'!J34/'Balance Sheet'!J67 -> 1.4353612 | ... P22: ='Balance Sheet'!P34/'Balance Sheet'!P67 -> 1.9362629 | S22: =MEDIAN(C22:P22) -> 1.5560963
B23: Quick Ratio | C23: =('Balance Sheet'!C34-'Balance Sheet'!C24)/'Balance Sheet'!C67 -> 1.4826322 | D23: =('Balance Sheet'!D34-'Balance Sheet'!D24)/'Balance Sheet'!D67 -> 1.1378924 | E23: =('Balance Sheet'!E34-'Balance Sheet'!E24)/'Balance Sheet'!E67 -> 0.92084709 | F23: =('Balance Sheet'!F34-'Balance Sheet'!F24)/'Balance Sheet'!F67 -> 0.63050922 | G23: =('Balance Sheet'!G34-'Balance Sheet'!G24)/'Balance Sheet'!G67 -> 0.85936774 | H23: =('Balance Sheet'!H34-'Balance Sheet'!H24)/'Balance Sheet'!H67 -> 0.89791182 | I23: =('Balance Sheet'!I34-'Balance Sheet'!I24)/'Balance Sheet'!I67 -> 0.73990537 | J23: =('Balance Sheet'!J34-'Balance Sheet'!J24)/'Balance Sheet'!J67 -> 1.0618246 | ... P23: =('Balance Sheet'!P34-'Balance Sheet'!P24)/'Balance Sheet'!P67 -> 1.8283738 | S23: =MEDIAN(C23:P23) -> 1.2451614
B25: TURNOVER RATIO
B26: Receivable Turnover Ratio | C26: ='Working Capital Schedule'!C30 -> 0 | D26: ='Working Capital Schedule'!D30 -> 32.464456 | E26: ='Working Capital Schedule'!E30 -> 45.482887 | F26: ='Working Capital Schedule'!F30 -> 47.984589 | G26: ='Working Capital Schedule'!G30 -> 49.330579 | H26: ='Working Capital Schedule'!H30 -> 46.434907 | I26: ='Working Capital Schedule'!I30 -> 42.622206 | J26: ='Working Capital Schedule'!J30 -> 44.053271 | ... P26: ='Working Capital Schedule'!P30 -> 44.053271 | S26: =MEDIAN(C26:P26) -> 44.053271
B27: Payable Turnover Ratio | C27: ='Working Capital Schedule'!C43 -> 0 | D27: ='Working Capital Schedule'!D43 -> 0.8902725 | E27: ='Working Capital Schedule'!E43 -> 0.98307611 | F27: ='Working Capital Schedule'!F43 -> 1.0324618 | G27: ='Working Capital Schedule'!G43 -> 0.96487253 | H27: ='Working Capital Schedule'!H43 -> 0.61208794 | I27: ='Working Capital Schedule'!I43 -> 0.47894642 | J27: ='Working Capital Schedule'!J43 -> 0.82695289 | ... P27: ='Working Capital Schedule'!P43 -> 0.82695289 | S27: =MEDIAN(C27:P27) -> 0.82695289
B28: Inventory Turnover Ratio | C28: ='Working Capital Schedule'!C17 -> 0 | D28: ='Working Capital Schedule'!D17 -> 9.1010812 | E28: ='Working Capital Schedule'!E17 -> 8.3233922 | F28: ='Working Capital Schedule'!F17 -> 7.1251495 | G28: ='Working Capital Schedule'!G17 -> 7.4910085 | H28: ='Working Capital Schedule'!H17 -> 7.9950389 | I28: ='Working Capital Schedule'!I17 -> 8.7719059 | J28: ='Working Capital Schedule'!J17 -> 8.134596 | ... P28: ='Working Capital Schedule'!P17 -> 8.0622195 | S28: =MEDIAN(C28:P28) -> 8.0545487
B29: Fixed Asset Turnover Ratio | C29: ='Income Statement'!C10/'Balance Sheet'!C44 -> 2.5792932 | D29: ='Income Statement'!D10/'Balance Sheet'!D44 -> 2.6134059 | E29: ='Income Statement'!E10/'Balance Sheet'!E44 -> 3.6652176 | F29: ='Income Statement'!F10/'Balance Sheet'!F44 -> 5.4673035 | G29: ='Income Statement'!G10/'Balance Sheet'!G44 -> 4.5730257 | H29: ='Income Statement'!H10/'Balance Sheet'!H44 -> 4.2282364 | I29: ='Income Statement'!I10/'Balance Sheet'!I44 -> 4.0952658 | J29: ='Income Statement'!J10/'Balance Sheet'!J44 -> 3.5419568 | ... P29: ='Income Statement'!P10/'Balance Sheet'!P44 -> 1.3855428 | S29: =MEDIAN(C29:P29) -> 2.8751665
B33: Receivable days | C33: ='Working Capital Schedule'!C32 -> 0 | D33: ='Working Capital Schedule'!D32 -> 11.243065 | E33: ='Working Capital Schedule'!E32 -> 8.0249963 | F33: ='Working Capital Schedule'!F32 -> 7.6066088 | G33: ='Working Capital Schedule'!G32 -> 7.3990617 | H33: ='Working Capital Schedule'!H32 -> 7.8604659 | I33: ='Working Capital Schedule'!I32 -> 8.5636112 | J33: ='Working Capital Schedule'!J32 -> 8.2854234 | ... P33: ='Working Capital Schedule'!P32 -> 8.2854234 | S33: =MEDIAN(C33:P33) -> 8.2854234
B34: Payable Days | C34: ='Working Capital Schedule'!C45 -> 0 | D34: ='Working Capital Schedule'!D45 -> 409.98683 | E34: ='Working Capital Schedule'!E45 -> 371.28356 | F34: ='Working Capital Schedule'!F45 -> 353.52397 | G34: ='Working Capital Schedule'!G45 -> 378.28831 | H34: ='Working Capital Schedule'!H45 -> 596.31954 | I34: ='Working Capital Schedule'!I45 -> 762.08942 | J34: ='Working Capital Schedule'!J45 -> 441.37944 | ... P34: ='Working Capital Schedule'!P45 -> 441.37944 | S34: =MEDIAN(C34:P34) -> 441.37944
B35: Inventory Days | C35: ='Working Capital Schedule'!C19 -> 0 | D35: ='Working Capital Schedule'!D19 -> 40.105125 | E35: ='Working Capital Schedule'!E19 -> 43.852313 | F35: ='Working Capital Schedule'!F19 -> 51.226996 | G35: ='Working Capital Schedule'!G19 -> 48.725082 | H35: ='Working Capital Schedule'!H19 -> 45.653311 | I35: ='Working Capital Schedule'!I19 -> 41.610114 | J35: ='Working Capital Schedule'!J19 -> 44.870083 | ... P35: ='Working Capital Schedule'!P19 -> 45.272893 | S35: =MEDIAN(C35:P35) -> 45.071488
B36: Cash Conversion Cycle | C36: =C35+C33-C34 -> 0 | D36: =D35+D33-D34 -> -358.63864 | E36: =E35+E33-E34 -> -319.40625 | F36: =F35+F33-F34 -> -294.69036 | G36: =G35+G33-G34 -> -322.16417 | H36: =H35+H33-H34 -> -542.80577 | I36: =I35+I33-I34 -> -711.9157 | J36: =J35+J33-J34 -> -388.22393 | ... P36: =P35+P33-P34 -> -387.82112 | S36: =MEDIAN(C36:P36) -> -387.52614
B39: CFO%Sales | C39: =CFS!C25/'Income Statement'!C10 -> 0.10455129 | D39: =CFS!D25/'Income Statement'!D10 -> 0.12801962 | E39: =CFS!E25/'Income Statement'!E10 -> 0.14097596 | F39: =CFS!F25/'Income Statement'!F10 -> 0.091928134 | G39: =CFS!G25/'Income Statement'!G10 -> 0.15497698 | H39: =CFS!H25/'Income Statement'!H10 -> 0.15343423 | I39: =CFS!I25/'Income Statement'!I10 -> 0.13825423 | J39: =CFS!J25/'Income Statement'!J10 -> 0.15257942 | ... P39: =CFS!P25/'Income Statement'!P10 -> 0.10281373 | S39: =MEDIAN(C39:P39) -> 0.1396151
B40: CFO%Totak Assets | D40: =CFS!D25/AVERAGE('Balance Sheet'!C36,'Balance Sheet'!D36) -> 0.21087258 | E40: =CFS!E25/AVERAGE('Balance Sheet'!D36,'Balance Sheet'!E36) -> 0.23366082 | F40: =CFS!F25/AVERAGE('Balance Sheet'!E36,'Balance Sheet'!F36) -> 0.16728941 | G40: =CFS!G25/AVERAGE('Balance Sheet'!F36,'Balance Sheet'!G36) -> 0.29931168 | H40: =CFS!H25/AVERAGE('Balance Sheet'!G36,'Balance Sheet'!H36) -> 0.27927286 | I40: =CFS!I25/AVERAGE('Balance Sheet'!H36,'Balance Sheet'!I36) -> 0.27698021 | J40: =CFS!J25/AVERAGE('Balance Sheet'!I36,'Balance Sheet'!J36) -> 0.30214746 | K40: =CFS!K25/AVERAGE('Balance Sheet'!J36,'Balance Sheet'!K36) -> 0.25797496 | ... P40: =CFS!P25/AVERAGE('Balance Sheet'!O36,'Balance Sheet'!P36) -> 0.078106196 | S40: =MEDIAN(C40:P40) -> 0.22733224
B41: CFO%Total Debt | D41: =CFS!D25/AVERAGE('Balance Sheet'!D54+'Balance Sheet'!D67,'Balance Sheet'!C54+'Balance Sheet'!C67) -> 0.5541305 | E41: =CFS!E25/AVERAGE('Balance Sheet'!E54+'Balance Sheet'!E67,'Balance Sheet'!D54+'Balance Sheet'!D67) -> 0.47311053 | F41: =CFS!F25/AVERAGE('Balance Sheet'!F54+'Balance Sheet'!F67,'Balance Sheet'!E54+'Balance Sheet'!E67) -> 0.27747985 | G41: =CFS!G25/AVERAGE('Balance Sheet'!G54+'Balance Sheet'!G67,'Balance Sheet'!F54+'Balance Sheet'!F67) -> 0.47086728 | H41: =CFS!H25/AVERAGE('Balance Sheet'!H54+'Balance Sheet'!H67,'Balance Sheet'!G54+'Balance Sheet'!G67) -> 0.47229014 | I41: =CFS!I25/AVERAGE('Balance Sheet'!I54+'Balance Sheet'!I67,'Balance Sheet'!H54+'Balance Sheet'!H67) -> 0.51870562 | J41: =CFS!J25/AVERAGE('Balance Sheet'!J54+'Balance Sheet'!J67,'Balance Sheet'!I54+'Balance Sheet'!I67) -> 0.60921618 | K41: =CFS!K25/AVERAGE('Balance Sheet'!K54+'Balance Sheet'!K67,'Balance Sheet'!J54+'Balance Sheet'!J67) -> 0.52599443 | ... P41: =CFS!P25/AVERAGE('Balance Sheet'!P54+'Balance Sheet'!P67,'Balance Sheet'!O54+'Balance Sheet'!O67) -> 0.14936793 | S41: =MEDIAN(C41:P41) -> 0.47229014
B44: Return on Capital employed | D44: =D52/D51 -> 0.40152763 | E44: =E52/E51 -> 0.5435999 | F44: =F52/F51 -> 0.57200332 | G44: =G52/G51 -> 0.65737987 | H44: =H52/H51 -> 0.6035521 | I44: =I52/I51 -> 0.60535348 | J44: =J52/J51 -> 0.68500718 | K44: =K52/K51 -> 0.58602854 | ... P44: =P52/P51 -> 0.50860051 | S44: =MEDIAN(C44:P44) -> 0.57200332
B45: Retained Earnings Percentage | C45: =('Income Statement'!C32--(CFS!C57))/'Income Statement'!C32 -> 0.69329964 | D45: =('Income Statement'!D32--(CFS!D57))/'Income Statement'!D32 -> 0.68963117 | E45: =('Income Statement'!E32--(CFS!E57))/'Income Statement'!E32 -> -0.52586472 | F45: =('Income Statement'!F32--(CFS!F57))/'Income Statement'!F32 -> -0.63912453 | G45: =('Income Statement'!G32--(CFS!G57))/'Income Statement'!G32 -> 0.41318989 | H45: =('Income Statement'!H32--(CFS!H57))/'Income Statement'!H32 -> 0.18824207 | I45: =('Income Statement'!I32--(CFS!I57))/'Income Statement'!I32 -> 0.18840513 | J45: =('Income Statement'!J32--(CFS!J57))/'Income Statement'!J32 -> 0.36914269 | ... P45: =('Income Statement'!P32--(CFS!P57))/'Income Statement'!P32 -> 0.78564638 | S45: =MEDIAN(C45:P45) -> 0.48399254
B46: Return on Equity | D46: ='Income Statement'!D32/AVERAGE('Balance Sheet'!D42,'Balance Sheet'!C42) -> 0.32199333 | E46: ='Income Statement'!E32/AVERAGE('Balance Sheet'!E42,'Balance Sheet'!D42) -> 0.46552854 | F46: ='Income Statement'!F32/AVERAGE('Balance Sheet'!F42,'Balance Sheet'!E42) -> 0.49657373 | G46: ='Income Statement'!G32/AVERAGE('Balance Sheet'!G42,'Balance Sheet'!F42) -> 0.7604003 | H46: ='Income Statement'!H32/AVERAGE('Balance Sheet'!H42,'Balance Sheet'!G42) -> 0.57096842 | I46: ='Income Statement'!I32/AVERAGE('Balance Sheet'!I42,'Balance Sheet'!H42) -> 0.52496011 | J46: ='Income Statement'!J32/AVERAGE('Balance Sheet'!J42,'Balance Sheet'!I42) -> 0.59481729 | K46: ='Income Statement'!K32/AVERAGE('Balance Sheet'!K42,'Balance Sheet'!J42) -> 0.50669911 | ... P46: ='Income Statement'!P32/AVERAGE('Balance Sheet'!P42,'Balance Sheet'!O42) -> 0.38037958 | S46: =MEDIAN(C46:P46) -> 0.49657373
B47: Interest Coverage Ratio | D47: =C52/'Income Statement'!C19 -> 195.49175 | E47: =D52/'Income Statement'!D19 -> 25.204291 | F47: =E52/'Income Statement'!E19 -> 23.671055 | G47: =F52/'Income Statement'!F19 -> 15.410631 | H47: =G52/'Income Statement'!G19 -> 16.713601 | I47: =H52/'Income Statement'!H19 -> 18.782744 | J47: =I52/'Income Statement'!I19 -> 22.263401 | K47: =J52/'Income Statement'!J19 -> 32.475612 | ... P47: =O52/'Income Statement'!O19 -> 9.4612602 | S47: =MEDIAN(C47:P47) -> 20.840612
B50: CAPITAL EMPLOYED | C50: ='Balance Sheet'!C36-'Balance Sheet'!C67 -> 4390.41 | D50: ='Balance Sheet'!D36-'Balance Sheet'!D67 -> 5263.77 | E50: ='Balance Sheet'!E36-'Balance Sheet'!E67 -> 4394.51 | F50: ='Balance Sheet'!F36-'Balance Sheet'!F67 -> 3380.27 | G50: ='Balance Sheet'!G36-'Balance Sheet'!G67 -> 5218.32 | H50: ='Balance Sheet'!H36-'Balance Sheet'!H67 -> 4989.15 | I50: ='Balance Sheet'!I36-'Balance Sheet'!I67 -> 5220.29 | J50: ='Balance Sheet'!J36-'Balance Sheet'!J67 -> 6587.9986 | ... P50: ='Balance Sheet'!P36-'Balance Sheet'!P67 -> 29433.8
B51: AVERAGE CAPITALL EMPLYOED | D51: =AVERAGE(D50,C50) -> 4827.09 | E51: =AVERAGE(E50,D50) -> 4829.14 | F51: =AVERAGE(F50,E50) -> 3887.39 | G51: =AVERAGE(G50,F50) -> 4299.295 | H51: =AVERAGE(H50,G50) -> 5103.735 | I51: =AVERAGE(I50,H50) -> 5104.72 | J51: =AVERAGE(J50,I50) -> 5904.1443 | K51: =AVERAGE(K50,J50) -> 7357.6989 | ... P51: =AVERAGE(P50,O50) -> 25812.626
B52: EBIT | C52: ='Income Statement'!C25+'Income Statement'!C19 -> 1777.02 | D52: ='Income Statement'!D25+'Income Statement'!D19 -> 1938.21 | E52: ='Income Statement'!E25+'Income Statement'!E19 -> 2625.12 | F52: ='Income Statement'!F25+'Income Statement'!F19 -> 2223.6 | G52: ='Income Statement'!G25+'Income Statement'!G19 -> 2826.27 | H52: ='Income Statement'!H25+'Income Statement'!H19 -> 3080.37 | I52: ='Income Statement'!I25+'Income Statement'!I19 -> 3090.16 | J52: ='Income Statement'!J25+'Income Statement'!J19 -> 4044.3812 | ... P52: ='Income Statement'!P25+'Income Statement'!P19 -> 13128.315
B53: EBITDA | C53: ='Income Statement'!C27+'Income Statement'!C20+'Income Statement'!C19 -> 1938.9 | D53: ='Income Statement'!D27+'Income Statement'!D20+'Income Statement'!D19 -> 2106.01 | E53: ='Income Statement'!E27+'Income Statement'!E20+'Income Statement'!E19 -> 2822.36 | F53: ='Income Statement'!F27+'Income Statement'!F20+'Income Statement'!F19 -> 2423.16 | G53: ='Income Statement'!G27+'Income Statement'!G20+'Income Statement'!G19 -> 3427.78 | H53: ='Income Statement'!H27+'Income Statement'!H20+'Income Statement'!H19 -> 3377.93 | I53: ='Income Statement'!I27+'Income Statement'!I20+'Income Statement'!I19 -> 3378.71 | J53: ='Income Statement'!J27+'Income Statement'!J20+'Income Statement'!J19 -> 3763.0501 | ... P53: ='Income Statement'!P27+'Income Statement'!P20+'Income Statement'!P19 -> 12799.516

Sheet Assumption Sheet
B1: Britannia Industries Limited
B2: ASSUMPTION SHEET
B4: Particulars | C4: 2019 | D4: 2020 | E4: 2021 | F4: 2022 | G4: 2023 | H4: 2024 | I4: 2025 | J4: 2026 | K4: 2027 | L4: 2028 | M4: 2029 | N4: 2030 | O4: 2031 | P4: 2032
C5: Actual | D5: Actual | E5: Actual | F5: Actual | G5: Actual | H5: Actual | I5: Actual | J5: Forecast | K5: Forecast | L5: Forecast | M5: Forecast | N5: Forecast | O5: Forecast | P5: Forecast
B6: Revenue Schedule(%)
B7: % change in Revenue | D7: ='Revenue Schedule'!D8 -> 0.049289576 | E7: ='Revenue Schedule'!E8 -> 0.13246979 | F7: ='Revenue Schedule'!F8 -> 0.076134999 | G7: ='Revenue Schedule'!G8 -> 0.15310202 | H7: ='Revenue Schedule'!H8 -> 0.028754858 | I7: ='Revenue Schedule'!I8 -> 0.069973231 | J7: ='Revenue Schedule'!J8 -> 0.076970554 | K7: ='Revenue Schedule'!K8 -> 0.084667609 | ... P7: ='Revenue Schedule'!P8 -> 0.13635803
B9: Cost Schedule (%)
B10: COGS | C10: ='Cost Schedule '!C15 -> 0.59354644 | D10: ='Cost Schedule '!D15 -> 0.59721886 | E10: ='Cost Schedule '!E15 -> 0.58054345 | F10: ='Cost Schedule '!F15 -> 0.61970422 | G10: ='Cost Schedule '!G15 -> 0.58840346 | H10: ='Cost Schedule '!H15 -> 0.56603716 | I10: ='Cost Schedule '!I15 -> 0.59099621 | J10: ='Cost Schedule '!J15 -> 0.58181228 | ... P10: ='Cost Schedule '!P15 -> 0.59
B12: Employee Expense | C12: ='Cost Schedule '!C25 -> 0.039966819 | D12: ='Cost Schedule '!D25 -> 0.041957662 | E12: ='Cost Schedule '!E25 -> 0.040147258 | F12: ='Cost Schedule '!F25 -> 0.03835951 | G12: ='Cost Schedule '!G25 -> 0.040390048 | H12: ='Cost Schedule '!H25 -> 0.042261828 | I12: ='Cost Schedule '!I25 -> 0.039268961 | J12: ='Cost Schedule '!J25 -> 0.040070086 | ... P12: ='Cost Schedule '!P25 -> 0.040336012
B14: Tax Expense | C14: ='Cost Schedule '!C33 -> 0.3464334 | D14: ='Cost Schedule '!D33 -> 0.24437456 | E14: ='Cost Schedule '!E33 -> 0.26377203 | F14: ='Cost Schedule '!F33 -> 0.27057782 | G14: ='Cost Schedule '!G33 -> 0.23623618 | H14: ='Cost Schedule '!H33 -> 0.26746457 | I14: ='Cost Schedule '!I33 -> 0.25583191 | J14: ='Cost Schedule '!J33 -> 0.25752762 | ... P14: ='Cost Schedule '!P33 -> 0.25752762
B16: Other Expenses | C16: ='Cost Schedule '!C29 -> 0.20968242 | D16: ='Cost Schedule '!D29 -> 0.20192249 | E16: ='Cost Schedule '!E29 -> 0.18828743 | F16: ='Cost Schedule '!F29 -> 0.1862013 | G16: ='Cost Schedule '!G29 -> 0.19753689 | H16: ='Cost Schedule '!H29 -> 0.2026743 | I16: ='Cost Schedule '!I29 -> 0.19210519 | J16: ='Cost Schedule '!J29 -> 0.19462942 | ... P16: ='Cost Schedule '!P29 -> 0.19462942
B18: Asset Schedule (%)
B19: Addition | C19: ='Asset Schedule'!C17 -> 0 | D19: ='Asset Schedule'!D17 -> 6.747985 | E19: ='Asset Schedule'!E17 -> 7.3849985 | F19: ='Asset Schedule'!F17 -> 7.9705115 | G19: ='Asset Schedule'!G17 -> 7.584191 | H19: ='Asset Schedule'!H17 -> 6.371158 | I19: ='Asset Schedule'!I17 -> 6.3427211 | J19: ='Asset Schedule'!J17 -> 7.0669275 | ... P19: ='Asset Schedule'!P17 -> 6.9831144
B21: Disposal | C21: ='Asset Schedule'!C23 -> 0 | D21: ='Asset Schedule'!D23 -> -0.00043997903 | E21: ='Asset Schedule'!E23 -> -0.001219951 | F21: ='Asset Schedule'!F23 -> -0.0017817171 | G21: ='Asset Schedule'!G23 -> -0.03649129 | H21: ='Asset Schedule'!H23 -> -0.024513119 | I21: ='Asset Schedule'!I23 -> -0.0016190267 | J21: ='Asset Schedule'!J23 -> -0.011010847 | ... P21: ='Asset Schedule'!P23 -> -0.013444118
B23: Depreciation | C23: ='Asset Schedule'!C28 -> 0 | D23: ='Asset Schedule'!D28 -> -0.19419547 | E23: ='Asset Schedule'!E28 -> -0.19581063 | F23: ='Asset Schedule'!F28 -> -0.17260032 | G23: ='Asset Schedule'!G28 -> -0.15793816 | H23: ='Asset Schedule'!H28 -> -0.18867605 | I23: ='Asset Schedule'!I28 -> -0.19561071 | J23: ='Asset Schedule'!J28 -> -0.18413856 | ... P23: ='Asset Schedule'!P28 -> -0.18311475
B25: Debt Schedule (%)
B26: New Borrowings | C26: ='Debt Schedule'!C20 -> 0 | D26: ='Debt Schedule'!D20 -> 0.062153273 | E26: ='Debt Schedule'!E20 -> 0 | F26: ='Debt Schedule'!F20 -> 0.049413353 | G26: ='Debt Schedule'!G20 -> 0 | H26: ='Debt Schedule'!H20 -> 0 | I26: ='Debt Schedule'!I20 -> 0 | J26: ='Debt Schedule'!J20 -> 0.015938089 | ... P26: ='Debt Schedule'!P20 -> 0.015938089
B28: Repayment | C28: ='Debt Schedule'!C26 -> 0 | D28: ='Debt Schedule'!D26 -> 0 | E28: ='Debt Schedule'!E26 -> 0 | F28: ='Debt Schedule'!F26 -> -0.023711133 | G28: ='Debt Schedule'!G26 -> -0.099336624 | H28: ='Debt Schedule'!H26 -> 0 | I28: ='Debt Schedule'!I26 -> 0 | J28: ='Debt Schedule'!J26 -> -0.02050796 | ... P28: ='Debt Schedule'!P26 -> -0.02050796
B30: Finance cost | C30: ='Debt Schedule'!C31 -> 0.13172004 | D30: ='Debt Schedule'!D31 -> 0.093095329 | E30: ='Debt Schedule'!E31 -> 0.061590239 | F30: ='Debt Schedule'!F31 -> 0.063386423 | G30: ='Debt Schedule'!G31 -> 0.062100054 | H30: ='Debt Schedule'!H31 -> 0.065316266 | I30: ='Debt Schedule'!I31 -> 0.084997459 | J30: ='Debt Schedule'!J31 -> 0.080315116 | ... P30: ='Debt Schedule'!P31 -> 0.080315116
B32: Working Capital Schedule (%)
B33: Inventory Turnover Ratio | D33: 9.1010812 | E33: 8.3233922 | F33: 7.1251495 | G33: 7.4910085 | H33: 7.9950389 | I33: 8.7719059 | J33: 8.134596 | K33: 7.9735152 | L33: 7.9152023 | M33: 8.0468778 | N33: 8.1395227 | O33: 8.1636033 | P33: 8.0622195
B35: Receivable Turnover Ratio | D35: 32.464456 | E35: 45.482887 | F35: 47.984589 | G35: 49.330579 | H35: 46.434907 | I35: 42.622206 | J35: 44.053271 | K35: 44.053271 | L35: 44.053271 | M35: 44.053271 | N35: 44.053271 | O35: 44.053271 | P35: 44.053271
B37: Payable Turnover Ratio | D37: 0.8902725 | E37: 0.98307611 | F37: 1.0324618 | G37: 0.96487253 | H37: 0.61208794 | I37: 0.47894642 | J37: 0.82695289 | K37: 0.82695289 | L37: 0.82695289 | M37: 0.82695289 | N37: 0.82695289 | O37: 0.82695289 | P37: 0.82695289

Sheet Revenue Schedule
B1: Britannia Industries Limited
B2: REVENUE SCHEDULE
B5: Particulars | C5: 2019 | D5: 2020 | E5: 2021 | F5: 2022 | G5: 2023 | H5: 2024 | I5: 2025 | J5: 2026 | K5: 2027 | L5: 2028 | M5: 2029 | N5: 2030 | O5: 2031 | P5: 2032
C6: Actual | D6: Actual | E6: Actual | F6: Actual | G6: Actual | H6: Actual | I6: Actual | J6: Forecast | K6: Forecast | L6: Forecast | M6: Forecast | N6: Forecast | O6: Forecast | P6: Forecast
B8: Revenue % Change : | D8: =D13/C13-1 -> 0.049289576 | E8: =E13/D13-1 -> 0.13246979 | F8: =F13/E13-1 -> 0.076134999 | G8: =G13/F13-1 -> 0.15310202 | H8: =H13/G13-1 -> 0.028754858 | I8: =I13/H13-1 -> 0.069973231 | J8: =I8+I8*10% -> 0.076970554 | K8: =J8+J8*10% -> 0.084667609 | L8: =K8+K8*10% -> 0.09313437 | M8: =L8+L8*10% -> 0.10244781 | N8: =M8+M8*10% -> 0.11269259 | O8: =N8+N8*10% -> 0.12396185 | P8: =O8+O8*10% -> 0.13635803
B10: Composition of revenue
B11: Revenue from sale of products | C11: ='Income Statement'!C8 -> 10973.46 | D11: ='Income Statement'!D8 -> 11443.99 | E11: ='Income Statement'!E8 -> 12883.04 | F11: ='Income Statement'!F8 -> 13944.67 | G11: ='Income Statement'!G8 -> 15984.9 | H11: 16546.21 | I11: 17535.02 | J11: =ROUND(J13*$J16,2) -> 19045.97 | K11: =ROUND(K13*$J16,2) -> 20658.55 | L11: =ROUND(L13*$J16,2) -> 22582.57 | M11: =ROUND(M13*$J16,2) -> 24896.1 | N11: =ROUND(N13*$J16,2) -> 27701.71 | O11: =ROUND(O13*$J16,2) -> 31135.66 | P11: =ROUND(P13*$J16,2) -> 35381.26
B12: Other operating revenue | C12: ='Income Statement'!C9 -> 81.21 | D12: ='Income Statement'!D9 -> 155.56 | E12: ='Income Statement'!E9 -> 253.1 | F12: ='Income Statement'!F9 -> 191.59 | G12: ='Income Statement'!G9 -> 315.65 | H12: 223.06 | I12: 407.65 | J12: =J13-J11 -> 277.75725 | K12: =K13-K11 -> 301.27104 | L12: =L13-L11 -> 329.33077 | M12: =M13-M11 -> 363.07476 | N12: =N13-N11 -> 403.98653 | O12: =O13-O11 -> 454.07058 | P12: =P13-P11 -> 515.98405
B13: Total | C13: =SUM(C11:C12) -> 11054.67 | D13: =SUM(D11:D12) -> 11599.55 | E13: =SUM(E11:E12) -> 13136.14 | F13: =SUM(F11:F12) -> 14136.26 | G13: =SUM(G11:G12) -> 16300.55 | H13: =SUM(H11:H12) -> 16769.27 | I13: =SUM(I11:I12) -> 17942.67 | J13: =I13*(1+J8) -> 19323.727 | K13: =J13*(1+K8) -> 20959.821 | L13: =K13*(1+L8) -> 22911.901 | M13: =L13*(1+M8) -> 25259.175 | N13: =M13*(1+N8) -> 28105.697 | O13: =N13*(1+O8) -> 31589.731 | P13: =O13*(1+P8) -> 35897.244
B15: Composition of revenue (%)
B16: Revenue from sale of products | C16: =C11/C13 -> 0.99265378 | D16: =D11/D13 -> 0.98658913 | E16: =E11/E13 -> 0.98073254 | F16: =F11/F13 -> 0.98644691 | G16: =G11/G13 -> 0.98063562 | H16: =H11/H13 -> 0.98669829 | I16: =I11/I13 -> 0.97728042 | J16: =AVERAGE(C16:H16) -> 0.98562605 | K16: 0.98562605 | L16: 0.98562605 | M16: 0.98562605 | N16: 0.98562605 | O16: 0.98562605 | P16: 0.98562605
B17: Other operating revenue | C17: =C12/C13 -> 0.0073462166 | D17: =D12/D13 -> 0.013410865 | E17: =E12/E13 -> 0.019267456 | F17: =F12/F13 -> 0.01355309 | G17: =G12/G13 -> 0.019364377 | H17: =AVERAGE(C17:G17) -> 0.014588401 | I17: 0.01 | J17: 0.01 | K17: 0.01 | L17: 0.01 | M17: 0.01 | N17: 0.01 | O17: 0.01 | P17: 0.01
B18: Total | C18: =SUM(C16:C17) -> 1 | D18: =SUM(D16:D17) -> 1 | E18: =SUM(E16:E17) -> 1 | F18: =SUM(F16:F17) -> 1 | G18: =SUM(G16:G17) -> 1 | H18: =SUM(H16:H17) -> 1.0012867 | I18: =SUM(I16:I17) -> 0.98728042 | J18: =SUM(J16:J17) -> 0.99562605 | ... P18: =SUM(P16:P17) -> 0.99562605

Sheet Cost Schedule 
B1: Britannia Industries Limited
B2: COST SCHEDULE
B4: Particulars | C4: 2019 | D4: 2020 | E4: 2021 | F4: 2022 | G4: 2023 | H4: 2024 | I4: 2025 | J4: 2026 | K4: 2027 | L4: 2028 | M4: 2029 | N4: 2030 | O4: 2031 | P4: 2032
C5: Actual | D5: Actual | E5: Actual | F5: Actual | G5: Actual | H5: Actual | I5: Actual | J5: Forecast | K5: Forecast | L5: Forecast | M5: Forecast | N5: Forecast | O5: Forecast | P5: Forecast
B7: Reveue from Operations | C7: ='Income Statement'!C10 -> 11054.67 | D7: ='Income Statement'!D10 -> 11599.55 | E7: ='Income Statement'!E10 -> 13136.14 | F7: ='Income Statement'!F10 -> 14136.26 | G7: ='Income Statement'!G10 -> 16300.55 | H7: ='Income Statement'!H10 -> 16769.27 | I7: ='Income Statement'!I10 -> 17942.67 | J7: ='Income Statement'!J10 -> 19323.727 | ... P7: ='Income Statement'!P10 -> 35897.244
B9: COGS / Adjusted Purchase(s)
B10: Cost of materials consumed | C10: ='Income Statement'!C14 -> 5513.01 | D10: ='Income Statement'!D14 -> 5901.16 | E10: ='Income Statement'!E14 -> 6502.33 | F10: ='Income Statement'!F14 -> 7473.97 | G10: ='Income Statement'!G14 -> 8326.7 | H10: ='Income Statement'!H14 -> 8546.89 | I10: ='Income Statement'!I14 -> 9859.45 | J10: =J13*$J18 -> 9791.2203 | K10: =K13*$J18 -> 10952.213 | L10: =L13*$J18 -> 11373.628 | M10: =M13*$J18 -> 12978.79 | N10: =N13*$J18 -> 15175.712 | O10: =O13*$J18 -> 16781.81 | P10: =P13*$J18 -> 18444.894
B11: Purchase of stock-in-trade | C11: ='Income Statement'!C15 -> 1103.63 | D11: ='Income Statement'!D15 -> 973.74 | E11: ='Income Statement'!E15 -> 1160.89 | F11: ='Income Statement'!F15 -> 1361.59 | G11: ='Income Statement'!G15 -> 1337.13 | H11: ='Income Statement'!H15 -> 941.48 | I11: ='Income Statement'!I15 -> 809.35 | J11: =J13*$J19 -> 1495.8295 | K11: =K13*$J19 -> 1673.1972 | L11: =L13*$J19 -> 1737.5779 | M11: =M13*$J19 -> 1982.8026 | N11: =N13*$J19 -> 2318.432 | O11: =O13*$J19 -> 2563.7996 | P11: =P13*$J19 -> 2817.8731
B12: Changes in inventories of finished good, work-in-progress, and stock-in-trade | C12: ='Income Statement'!C16 -> -55.18 | D12: ='Income Statement'!D16 -> 52.57 | E12: ='Income Statement'!E16 -> -37.12 | F12: ='Income Statement'!F16 -> -75.26 | G12: ='Income Statement'!G16 -> -72.53 | H12: ='Income Statement'!H16 -> 3.66 | I12: ='Income Statement'!I16 -> -64.75 | J12: =J13*J20 -> -44.268038 | K12: =K13*K20 -> -49.517113 | L12: =L13*L20 -> -51.422415 | M12: =M13*M20 -> -58.67967 | N12: =N13*N20 -> -68.612388 | O12: =O13*O20 -> -75.873873 | P12: =P13*P20 -> -83.393003
B13: Total | C13: ='Income Statement'!C17 -> 6561.46 | D13: ='Income Statement'!D17 -> 6927.47 | E13: ='Income Statement'!E17 -> 7626.1 | F13: ='Income Statement'!F17 -> 8760.3 | G13: ='Income Statement'!G17 -> 9591.3 | H13: ='Income Statement'!H17 -> 9492.03 | I13: ='Income Statement'!I17 -> 10604.05 | J13: =J7*J15 -> 11242.782 | K13: =K7*K15 -> 12575.893 | L13: =L7*L15 -> 13059.783 | M13: =M7*M15 -> 14902.913 | N13: =N7*N15 -> 17425.532 | O13: =O7*O15 -> 19269.736 | P13: =P7*P15 -> 21179.374
B15: Total as a % of Revenue from Operations | C15: =C13/C7 -> 0.59354644 | D15: =D13/D7 -> 0.59721886 | E15: =E13/E7 -> 0.58054345 | F15: =F13/F7 -> 0.61970422 | G15: =G13/G7 -> 0.58840346 | H15: =H13/H7 -> 0.56603716 | I15: =I13/I7 -> 0.59099621 | J15: =AVERAGE(G15:I15) -> 0.58181228 | K15: 0.6 | L15: 0.57 | M15: 0.59 | N15: 0.62 | O15: 0.61 | P15: 0.59
B17: COGS / Adjusted Purchase(s) (in %)
B18: Cost of materials consumed | C18: =C10/C13 -> 0.84021087 | D18: =D10/D13 -> 0.85184923 | E18: =E10/E13 -> 0.85264159 | F18: =F10/F13 -> 0.8531637 | G18: =G10/G13 -> 0.86815135 | H18: =H10/H13 -> 0.90042804 | I18: =I10/I13 -> 0.92978155 | J18: =AVERAGE(C18:I18) -> 0.87088947 | K18: 0.87088947 | L18: 0.87088947 | M18: 0.87088947 | N18: 0.87088947 | O18: 0.87088947 | P18: 0.87088947
B19: Purchase of stock-in-trade | C19: =C11/C13 -> 0.16819885 | D19: =D11/D13 -> 0.14056214 | E19: =E11/E13 -> 0.15222591 | F19: =F11/F13 -> 0.15542733 | G19: =G11/G13 -> 0.13941072 | H19: =H11/H13 -> 0.09918637 | I19: =I11/I13 -> 0.076324612 | J19: =AVERAGE(C19:I19) -> 0.13304799 | K19: 0.13304799 | L19: 0.13304799 | M19: 0.13304799 | N19: 0.13304799 | O19: 0.13304799 | P19: 0.13304799
B20: Changes in inventories of finished good, work-in-progress, and stock-in-trade | C20: =C12/C13 -> -0.0084097137 | D20: =D12/D13 -> 0.007588629 | E20: =E12/E13 -> -0.0048674945 | F20: =F12/F13 -> -0.00859103 | G20: =G12/G13 -> -0.0075620615 | H20: =H12/H13 -> 0.00038558664 | I20: =I12/I13 -> -0.0061061576 | J20: =AVERAGE(C20:I20) -> -0.0039374631 | K20: -0.0039374631 | L20: -0.0039374631 | M20: -0.0039374631 | N20: -0.0039374631 | O20: -0.0039374631 | P20: -0.0039374631
B21: Total | C21: =SUM(C18:C20) -> 1 | D21: =SUM(D18:D20) -> 1 | E21: =SUM(E18:E20) -> 1 | F21: =SUM(F18:F20) -> 1 | G21: =SUM(G18:G20) -> 1 | H21: =SUM(H18:H20) -> 1 | I21: =SUM(I18:I20) -> 1 | J21: =SUM(J18:J20) -> 1 | ... P21: =SUM(P18:P20) -> 1
B24: Employee Benefits Expense | C24: ='Income Statement'!C18 -> 441.82 | D24: ='Income Statement'!D18 -> 486.69 | E24: ='Income Statement'!E18 -> 527.38 | F24: ='Income Statement'!F18 -> 542.26 | G24: ='Income Statement'!G18 -> 658.38 | H24: ='Income Statement'!H18 -> 708.7 | I24: ='Income Statement'!I18 -> 704.59 | J24: =J7*$J25 -> 774.30342 | K24: =K7*$J25 -> 839.86184 | L24: =L7*$J25 -> 918.08185 | M24: =M7*$J25 -> 1012.1373 | N24: =N7*$J25 -> 1126.1977 | O24: =O7*$J25 -> 1265.8032 | P24: =P7*$J25 -> 1438.4057
B25: Employee Benefits Expense as a % of Revenue from Operations | C25: =C24/C7 -> 0.039966819 | D25: =D24/D7 -> 0.041957662 | E25: =E24/E7 -> 0.040147258 | F25: =F24/F7 -> 0.03835951 | G25: =G24/G7 -> 0.040390048 | H25: =H24/H7 -> 0.042261828 | I25: =I24/I7 -> 0.039268961 | J25: =AVERAGE(F25:I25) -> 0.040070086 | K25: 0.040336012 | L25: 0.040336012 | M25: 0.040336012 | N25: 0.040336012 | O25: 0.040336012 | P25: 0.040336012
B28: Other Expenses | C28: ='Income Statement'!C21 -> 2317.97 | D28: ='Income Statement'!D21 -> 2342.21 | E28: ='Income Statement'!E21 -> 2473.37 | F28: ='Income Statement'!F21 -> 2632.19 | G28: ='Income Statement'!G21 -> 3219.96 | H28: ='Income Statement'!H21 -> 3398.7 | I28: ='Income Statement'!I21 -> 3446.88 | J28: =J7*$J29 -> 3760.9658 | K28: =K7*$J29 -> 4079.3978 | L28: =L7*$J29 -> 4459.3299 | M28: =M7*$J29 -> 4916.1785 | N28: =N7*$J29 -> 5470.1954 | O28: =O7*$J29 -> 6148.2909 | P28: =P7*$J29 -> 6986.6598
B29: Other Expenses as a % of Revenue from Operations | C29: =C28/C7 -> 0.20968242 | D29: =D28/D7 -> 0.20192249 | E29: =E28/E7 -> 0.18828743 | F29: =F28/F7 -> 0.1862013 | G29: =G28/G7 -> 0.19753689 | H29: =H28/H7 -> 0.2026743 | I29: =I28/I7 -> 0.19210519 | J29: =AVERAGE(F29:I29) -> 0.19462942 | K29: 0.19462942 | L29: 0.19462942 | M29: 0.19462942 | N29: 0.19462942 | O29: 0.19462942 | P29: 0.19462942
B32: Tax Expense | C32: ='Income Statement'!C31 -> 612.47 | D32: ='Income Statement'!D31 -> 450.7 | E32: ='Income Statement'!E31 -> 663.02 | F32: ='Income Statement'!F31 -> 562.35 | G32: ='Income Statement'!G31 -> 716.45 | H32: ='Income Statement'!H31 -> 779.25 | I32: ='Income Statement'!I31 -> 748.71 | J32: =$J33*'Income Statement'!J27 -> 1009.4684 | K32: =$J33*'Income Statement'!K27 -> 1062.0624 | L32: =$J33*'Income Statement'!L27 -> 1430.4215 | M32: =$J33*'Income Statement'!M27 -> 1578.2049 | N32: =$J33*'Income Statement'!N27 -> 1691.0223 | O32: =$J33*'Income Statement'!O27 -> 2182.4104 | P32: =$J33*'Income Statement'!P27 -> 2970.9343
B33: Effective Tax Rate (Tax Expense/PBT) | C33: =C32/'Income Statement'!C27 -> 0.3464334 | D33: =D32/'Income Statement'!D27 -> 0.24437456 | E33: =E32/'Income Statement'!E27 -> 0.26377203 | F33: =F32/'Income Statement'!F27 -> 0.27057782 | G33: =G32/'Income Statement'!G27 -> 0.23623618 | H33: =H32/'Income Statement'!H27 -> 0.26746457 | I33: =I32/'Income Statement'!I27 -> 0.25583191 | J33: =AVERAGE(F33:I33) -> 0.25752762 | K33: 0.25752762 | L33: 0.25752762 | M33: 0.25752762 | N33: 0.25752762 | O33: 0.25752762 | P33: 0.25752762
B35: Composition of Tax Expense
B36: Current Tax | C36: ='Income Statement'!C29 -> 599.78 | D36: ='Income Statement'!D29 -> 447.69 | E36: ='Income Statement'!E29 -> 657.12 | F36: ='Income Statement'!F29 -> 612.24 | G36: ='Income Statement'!G29 -> 720.97 | H36: ='Income Statement'!H29 -> 765.69 | I36: ='Income Statement'!I29 -> 741.68 | J36: =J38*$J41 -> 1026.6887 | K36: =K38*$J41 -> 1080.1799 | L36: =L38*$J41 -> 1454.8228 | M36: =M38*$J41 -> 1605.1271 | N36: =N38*$J41 -> 1719.869 | O36: =O38*$J41 -> 2219.6396 | P36: =P38*$J41 -> 3021.6148
B37: Deferred Tax | C37: ='Income Statement'!C30 -> 12.69 | D37: ='Income Statement'!D30 -> 3.01 | E37: ='Income Statement'!E30 -> 5.9 | F37: ='Income Statement'!F30 -> -49.89 | G37: ='Income Statement'!G30 -> -4.52 | H37: ='Income Statement'!H30 -> 13.56 | I37: ='Income Statement'!I30 -> 7.03 | J37: =J38*$J42 -> -17.220281 | K37: =K38*$J42 -> -18.117469 | L37: =L38*$J42 -> -24.401219 | M37: =M38*$J42 -> -26.92222 | N37: =N38*$J42 -> -28.846745 | O37: =O38*$J42 -> -37.229217 | P37: =P38*$J42 -> -50.680459
B38: Total | C38: ='Income Statement'!C31 -> 612.47 | D38: ='Income Statement'!D31 -> 450.7 | E38: ='Income Statement'!E31 -> 663.02 | F38: ='Income Statement'!F31 -> 562.35 | G38: ='Income Statement'!G31 -> 716.45 | H38: ='Income Statement'!H31 -> 779.25 | I38: ='Income Statement'!I31 -> 748.71 | J38: =J32 -> 1009.4684 | K38: =K32 -> 1062.0624 | L38: =L32 -> 1430.4215 | M38: =M32 -> 1578.2049 | N38: =N32 -> 1691.0223 | O38: =O32 -> 2182.4104 | P38: =P32 -> 2970.9343
B40: Composition of Tax Expense in %
B41: Current Tax | C41: =C36/C38 -> 0.97928062 | D41: =D36/D38 -> 0.9933215 | E41: =E36/E38 -> 0.99110132 | F41: =F36/F38 -> 1.088717 | G41: =G36/G38 -> 1.0063089 | H41: =H36/H38 -> 0.98259865 | I41: =I36/I38 -> 0.99061052 | J41: =AVERAGE(F41:I41) -> 1.0170588 | K41: 1.0170588 | L41: 1.0170588 | M41: 1.0170588 | N41: 1.0170588 | O41: 1.0170588 | P41: 1.0170588
B42: Deferred Tax | C42: =C37/C38 -> 0.020719382 | D42: =D37/D38 -> 0.0066785001 | E42: =E37/E38 -> 0.0088986758 | F42: =F37/F38 -> -0.088716991 | G42: =G37/G38 -> -0.0063088841 | H42: =H37/H38 -> 0.017401347 | I42: =I37/I38 -> 0.0093894832 | J42: =AVERAGE(F42:I42) -> -0.017058761 | K42: -0.017058761 | L42: -0.017058761 | M42: -0.017058761 | N42: -0.017058761 | O42: -0.017058761 | P42: -0.017058761
B43: Total | C43: =SUM(C41:C42) -> 1 | D43: =SUM(D41:D42) -> 1 | E43: =SUM(E41:E42) -> 1 | F43: =SUM(F41:F42) -> 1 | G43: =SUM(G41:G42) -> 1 | H43: =SUM(H41:H42) -> 1 | I43: =SUM(I41:I42) -> 1 | J43: =AVERAGE(C43:I43) -> 1 | K43: 1 | L43: 1 | M43: 1 | N43: 1 | O43: 1 | P43: 1

Sheet Asset Schedule
B1: Britannia Industries Limited
B2: ASSET SCHEDULE
B4: Particulars | C4: 2019 | D4: 2020 | E4: 2021 | F4: 2022 | G4: 2023 | H4: 2024 | I4: 2025 | J4: 2026 | K4: 2027 | L4: 2028 | M4: 2029 | N4: 2030 | O4: 2031 | P4: 2032
C5: Actual | D5: Actual | E5: Actual | F5: Actual | G5: Actual | H5: Actual | I5: Actual | J5: Forecast | K5: Forecast | L5: Forecast | M5: Forecast | N5: Forecast | O5: Forecast | P5: Forecast
B7: Opening Balance | D7: =C12 -> 1659.17 | E7: =D12 -> 1778.76 | F7: =E12 -> 1773.57 | G7: =F12 -> 2149.28 | H7: =G12 -> 2632.06 | I7: =H12 -> 2828.86 | J7: =I12 -> 2860.22 | K7: =J12 -> 2742.8209 | ... P7: =O12 -> 2954.362
B8: Addition | C8: =C16 -> 401.21 | D8: =D16 -> 244.17 | E8: =E16 -> 242.07 | F8: =F16 -> 550.18 | G8: =G16 -> 711.46 | H8: =H16 -> 552.87 | I8: =I16 -> 374.85 | J8: =J16 -> 195.42542 | ... P8: =P16 -> 616.84705
B9: Disposal | C9: =C22 -> -1.82 | D9: =D22 -> -0.73 | E9: =E22 -> -2.17 | F9: =F22 -> -3.16 | G9: =G22 -> -78.43 | H9: =H22 -> -64.52 | I9: =I22 -> -4.58 | J9: =J22 -> -31.493445 | ... P9: =P22 -> -32.530029
B10: Depreciation | C10: =C27 -> -161.88 | D10: =D27 -> -184.81 | E10: =E27 -> -197.85 | F10: =F27 -> -200.54 | G10: =G27 -> -225.91 | H10: =H27 -> -300.46 | I10: =I27 -> -313.34 | J10: =J27 -> -281.33107 | ... P10: =P27 -> -328.79864
B11: Adjustments | D11: =D12-SUM(D7:D10) -> 60.96 | E11: =E12-SUM(E7:E10) -> -47.24 | F11: =F12-SUM(F7:F10) -> 29.23 | G11: =G12-SUM(G7:G10) -> 75.66 | H11: =H12-SUM(H7:H10) -> 8.91 | I11: =I12-SUM(I7:I10) -> -25.57
B12: Closing Balance | C12: =SUM('Balance Sheet'!C8:C12)-'Balance Sheet'!C11 -> 1659.17 | D12: =SUM('Balance Sheet'!D8:D12)-'Balance Sheet'!D11 -> 1778.76 | E12: =SUM('Balance Sheet'!E8:E12)-'Balance Sheet'!E11 -> 1773.57 | F12: =SUM('Balance Sheet'!F8:F12)-'Balance Sheet'!F11 -> 2149.28 | G12: =SUM('Balance Sheet'!G8:G12)-'Balance Sheet'!G11 -> 2632.06 | H12: =SUM('Balance Sheet'!H8:H12)-'Balance Sheet'!H11 -> 2828.86 | I12: =SUM('Balance Sheet'!I8:I12)-'Balance Sheet'!I11 -> 2860.22 | J12: =SUM(J7:J10) -> 2742.8209 | K12: =SUM(K7:K10) -> 2668.7201 | L12: =SUM(L7:L10) -> 2644.1044 | M12: =SUM(M7:M10) -> 2679.2173 | N12: =SUM(N7:N10) -> 2782.1454 | O12: =SUM(O7:O10) -> 2954.362 | P12: =SUM(P7:P10) -> 3209.8804
B14: Addition
B16: CAPEX | C16: =-CFS!C28 -> 401.21 | D16: =-CFS!D28 -> 244.17 | E16: =-CFS!E28 -> 242.07 | F16: =-CFS!F28 -> 550.18 | G16: =-CFS!G28 -> 711.46 | H16: =-CFS!H28 -> 552.87 | I16: =-CFS!I28 -> 374.85 | J16: =('Income Statement'!J10-'Income Statement'!I10)/J17 -> 195.42542 | K16: =('Income Statement'!K10-'Income Statement'!J10)/K17 -> 229.78572 | L16: =('Income Statement'!L10-'Income Statement'!K10)/L17 -> 275.87598 | M16: =('Income Statement'!M10-'Income Statement'!L10)/M17 -> 338.8667 | N16: =('Income Statement'!N10-'Income Statement'!M10)/N17 -> 417.5453 | O16: =('Income Statement'!O10-'Income Statement'!N10)/O17 -> 505.54575 | P16: =('Income Statement'!P10-'Income Statement'!O10)/P17 -> 616.84705
B17: Asset turnover ratio | D17: ='Income Statement'!D10/D18 -> 6.747985 | E17: ='Income Statement'!E10/E7 -> 7.3849985 | F17: ='Income Statement'!F10/F7 -> 7.9705115 | G17: ='Income Statement'!G10/G7 -> 7.584191 | H17: ='Income Statement'!H10/H7 -> 6.371158 | I17: ='Income Statement'!I10/I7 -> 6.3427211 | J17: =AVERAGE(D17:I17) -> 7.0669275 | K17: =AVERAGE(E17:J17) -> 7.1200846 | L17: =AVERAGE(F17:K17) -> 7.0759323 | M17: =AVERAGE(G17:L17) -> 6.9268357 | N17: =AVERAGE(H17:M17) -> 6.8172765 | O17: =AVERAGE(I17:N17) -> 6.8916296 | P17: =AVERAGE(J17:O17) -> 6.9831144
B18: Average Assets | C18: =AVERAGE(C7,C12) -> 1659.17 | D18: =AVERAGE(D7,D12) -> 1718.965 | E18: =AVERAGE(E7,E12) -> 1776.165 | F18: =AVERAGE(F7,F12) -> 1961.425 | G18: =AVERAGE(G7,G12) -> 2390.67 | H18: =AVERAGE(H7,H12) -> 2730.46 | I18: =AVERAGE(I7,I12) -> 2844.54 | J18: =AVERAGE(J7,J12) -> 2801.5205 | ... P18: =AVERAGE(P7,P12) -> 3082.1212
B20: Disposal
B22: SALE OF ASSETS | C22: =-(CFS!C30) -> -1.82 | D22: =-(CFS!D30) -> -0.73 | E22: =-(CFS!E30) -> -2.17 | F22: =-(CFS!F30) -> -3.16 | G22: =-(CFS!G30) -> -78.43 | H22: =-(CFS!H30) -> -64.52 | I22: =-(CFS!I30) -> -4.58 | J22: =J7*$J23 -> -31.493445 | K22: =K7*$J23 -> -30.200782 | L22: =L7*$J23 -> -29.384869 | M22: =M7*$J23 -> -29.113829 | N22: =N7*$J23 -> -29.500452 | O22: =O7*$J23 -> -30.633778 | P22: =P7*$J23 -> -32.530029
D23: =D22/D7 -> -0.00043997903 | E23: =E22/E7 -> -0.001219951 | F23: =F22/F7 -> -0.0017817171 | G23: =G22/G7 -> -0.03649129 | H23: =H22/H7 -> -0.024513119 | I23: =I22/I7 -> -0.0016190267 | J23: =AVERAGE(D23:I23) -> -0.011010847 | K23: =AVERAGE(E23:J23) -> -0.012772659 | L23: =AVERAGE(F23:K23) -> -0.01469811 | M23: =AVERAGE(G23:L23) -> -0.016850842 | N23: =AVERAGE(H23:M23) -> -0.013577434 | O23: =AVERAGE(I23:N23) -> -0.01175482 | P23: =AVERAGE(J23:O23) -> -0.013444118
B25: Depreciation
B27: DEPRECIATION | C27: =-CFS!C9 -> -161.88 | D27: =-CFS!D9 -> -184.81 | E27: =-CFS!E9 -> -197.85 | F27: =-CFS!F9 -> -200.54 | G27: =-CFS!G9 -> -225.91 | H27: =-CFS!H9 -> -300.46 | I27: =-CFS!I9 -> -313.34 | J27: =$J28*AVERAGE(J7:J8) -> -281.33107 | K27: =$J28*AVERAGE(K7:K8) -> -273.68575 | L27: =$J28*AVERAGE(L7:L8) -> -271.10684 | M27: =$J28*AVERAGE(M7:M8) -> -274.63999 | N27: =$J28*AVERAGE(N7:N8) -> -285.11669 | O27: =$J28*AVERAGE(O7:O8) -> -302.69535 | P27: =$J28*AVERAGE(P7:P8) -> -328.79864
D28: =D27/AVERAGE(D7:D8) -> -0.19419547 | E28: =E27/AVERAGE(E7:E8) -> -0.19581063 | F28: =F27/AVERAGE(F7:F8) -> -0.17260032 | G28: =G27/AVERAGE(G7:G8) -> -0.15793816 | H28: =H27/AVERAGE(H7:H8) -> -0.18867605 | I28: =I27/AVERAGE(I7:I8) -> -0.19561071 | J28: =AVERAGE(D28:I28) -> -0.18413856 | K28: =AVERAGE(E28:J28) -> -0.1824624 | L28: =AVERAGE(F28:K28) -> -0.1802377 | M28: =AVERAGE(G28:L28) -> -0.1815106 | N28: =AVERAGE(H28:M28) -> -0.18543934 | O28: =AVERAGE(I28:N28) -> -0.18489988 | P28: =AVERAGE(J28:O28) -> -0.18311475
B30: Composition of Fixed Assets
B31: Property, plant and equipment | C31: ='Balance Sheet'!C8/C36 -> 0.92551095 | D31: ='Balance Sheet'!D8/D36 -> 0.964925 | E31: ='Balance Sheet'!E8/E36 -> 0.92147477 | F31: ='Balance Sheet'!F8/F36 -> 0.73701426 | G31: ='Balance Sheet'!G8/G36 -> 0.9392605 | H31: ='Balance Sheet'!H8/H36 -> 0.92013744 | I31: ='Balance Sheet'!I8/I36 -> 0.9560838 | J31: =AVERAGE(C31:I31) -> 0.90920096 | K31: =AVERAGE(C31:J31) -> 0.90920096 | L31: 0.90920096 | M31: 0.90920096 | N31: 0.90920096 | O31: 0.90920096 | P31: 0.90920096
B32: Capital work-in-progress | C32: ='Balance Sheet'!C9/C36 -> 0.061018461 | D32: ='Balance Sheet'!D9/D36 -> 0.02223459 | E32: ='Balance Sheet'!E9/E36 -> 0.065697999 | F32: ='Balance Sheet'!F9/F36 -> 0.24923695 | G32: ='Balance Sheet'!G9/G36 -> 0.039892708 | H32: ='Balance Sheet'!H9/H36 -> 0.066295257 | I32: ='Balance Sheet'!I9/I36 -> 0.031186412 | J32: =AVERAGE(C32:I32) -> 0.076508912 | K32: =AVERAGE(C32:J32) -> 0.076508912 | L32: 0.076508912 | M32: 0.076508912 | N32: 0.076508912 | O32: 0.076508912 | P32: 0.076508912
B33: Investment property | C33: ='Balance Sheet'!C10/C36 -> 0.0088779329 | D33: ='Balance Sheet'!D10/D36 -> 0.0081348805 | E33: ='Balance Sheet'!E10/E36 -> 0.0080120886 | F33: ='Balance Sheet'!F10/F36 -> 0.0064905457 | G33: ='Balance Sheet'!G10/G36 -> 0.015436578 | H33: ='Balance Sheet'!H10/H36 -> 0.0097141605 | I33: ='Balance Sheet'!I10/I36 -> 0.010104118 | J33: =AVERAGE(C33:I33) -> 0.0095386149 | K33: =AVERAGE(C33:J33) -> 0.0095386149 | L33: 0.0095386149 | M33: 0.0095386149 | N33: 0.0095386149 | O33: 0.0095386149 | P33: 0.0095386149
B34: Other intangible assets | C34: ='Balance Sheet'!C12/C36 -> 0.0045926578 | D34: ='Balance Sheet'!D12/D36 -> 0.0047055252 | E34: ='Balance Sheet'!E12/E36 -> 0.0048151469 | F34: ='Balance Sheet'!F12/F36 -> 0.0072582446 | G34: ='Balance Sheet'!G12/G36 -> 0.005410211 | H34: ='Balance Sheet'!H12/H36 -> 0.0038531423 | I34: ='Balance Sheet'!I12/I36 -> 0.0026256722 | J34: =AVERAGE(C34:I34) -> 0.0047515143 | K34: =AVERAGE(C34:J34) -> 0.0047515143 | L34: 0.0047515143 | M34: 0.0047515143 | N34: 0.0047515143 | O34: 0.0047515143 | P34: 0.0047515143
B36: Total | C36: =C12 -> 1659.17 | D36: =D12 -> 1778.76 | E36: =E12 -> 1773.57 | F36: =F12 -> 2149.28 | G36: =G12 -> 2632.06 | H36: =H12 -> 2828.86 | I36: =I12 -> 2860.22 | J36: =J12 -> 2742.8209 | ... P36: =P12 -> 3209.8804
B39: Composition of Fixed Assets
B40: Property, plant and equipment | C40: ='Balance Sheet'!C8 -> 1535.58 | D40: ='Balance Sheet'!D8 -> 1716.37 | E40: ='Balance Sheet'!E8 -> 1634.3 | F40: ='Balance Sheet'!F8 -> 1584.05 | G40: ='Balance Sheet'!G8 -> 2472.19 | H40: ='Balance Sheet'!H8 -> 2602.94 | I40: ='Balance Sheet'!I8 -> 2734.61 | J40: =J45*J31 -> 2493.7754 | K40: =K45*K31 -> 2426.4029 | L40: =L45*L31 -> 2404.0222 | M40: =M45*M31 -> 2435.9469 | N40: =N45*N31 -> 2529.5293 | O40: =O45*O31 -> 2686.1088 | P40: =P45*P31 -> 2918.4263
B41: Capital work-in-progress | C41: ='Balance Sheet'!C9 -> 101.24 | D41: ='Balance Sheet'!D9 -> 39.55 | E41: ='Balance Sheet'!E9 -> 116.52 | F41: ='Balance Sheet'!F9 -> 535.68 | G41: ='Balance Sheet'!G9 -> 105 | H41: ='Balance Sheet'!H9 -> 187.54 | I41: ='Balance Sheet'!I9 -> 89.2 | J41: =J32*J45 -> 209.85024 | K41: =K32*K45 -> 204.18087 | L41: =L32*L45 -> 202.29755 | M41: =M32*M45 -> 204.984 | N41: =N32*N45 -> 212.85892 | O41: =O32*O45 -> 226.03502 | P41: =P32*P45 -> 245.58446
B42: Investment property | C42: ='Balance Sheet'!C10 -> 14.73 | D42: ='Balance Sheet'!D10 -> 14.47 | E42: ='Balance Sheet'!E10 -> 14.21 | F42: ='Balance Sheet'!F10 -> 13.95 | G42: ='Balance Sheet'!G10 -> 40.63 | H42: ='Balance Sheet'!H10 -> 27.48 | I42: ='Balance Sheet'!I10 -> 28.9 | J42: =J45*J33 -> 26.162712 | K42: =K45*K33 -> 25.455893 | L42: =L45*L33 -> 25.221093 | M42: =M45*M33 -> 25.556022 | N42: =N45*N33 -> 26.537814 | O42: =O45*O33 -> 28.180522 | P42: =P45*P33 -> 30.617813
B43: Other intangible assets | C43: ='Balance Sheet'!C12 -> 7.62 | D43: ='Balance Sheet'!D12 -> 8.37 | E43: ='Balance Sheet'!E12 -> 8.54 | F43: ='Balance Sheet'!F12 -> 15.6 | G43: ='Balance Sheet'!G12 -> 14.24 | H43: ='Balance Sheet'!H12 -> 10.9 | I43: ='Balance Sheet'!I12 -> 7.51 | J43: =J34*J45 -> 13.032553 | K43: =K34*K45 -> 12.680462 | L43: =L34*L45 -> 12.5635 | M43: =M34*M45 -> 12.730339 | N43: =N34*N45 -> 13.219404 | O43: =O34*O45 -> 14.037693 | P43: =P34*P45 -> 15.251793
B45: Total | C45: =C36 -> 1659.17 | D45: =D36 -> 1778.76 | E45: =E36 -> 1773.57 | F45: =F36 -> 2149.28 | G45: =G36 -> 2632.06 | H45: =H36 -> 2828.86 | I45: =I36 -> 2860.22 | J45: =J36 -> 2742.8209 | ... P45: =P36 -> 3209.8804

Sheet Sheet1

Sheet Debt Schedule
B1: Britannia Industries Limited
B2: DEBT SCHEDULE
B5: Particulars | C5: 2019 | D5: 2020 | E5: 2021 | F5: 2022 | G5: 2023 | H5: 2024 | I5: 2025 | J5: 2026 | K5: 2027 | L5: 2028 | M5: 2029 | N5: 2030 | O5: 2031 | P5: 2032
C6: Actual | D6: Actual | E6: Actual | F6: Actual | G6: Actual | H6: Actual | I6: Actual | J6: Forecast | K6: Forecast | L6: Forecast | M6: Forecast | N6: Forecast | O6: Forecast | P6: Forecast
B8: LONG TERM BORROWINGS :
B10: Opening balance | D10: =C15 -> 61.92 | E10: =D15 -> 766.06 | F10: =E15 -> 747.75 | G10: =F15 -> 706.99 | H10: =G15 -> 1551.8 | I10: =H15 -> 904.72 | J10: =I15 -> 712.94 | K10: =J15 -> 1006.3023 | ... P10: =O15 -> 2886.3974
B11: New borrowings | C11: =C19 -> 0 | D11: =D19 -> 720.95 | E11: =E19 -> 0 | F11: =F19 -> 698.52 | G11: =G19 -> 0 | H11: =H19 -> 0 | I11: =I19 -> 0 | J11: =J19 -> 307.98329 | ... P11: =P19 -> 572.13348
B12: Repayment | C12: =C25 -> 0 | D12: =D25 -> 0 | E12: =E25 -> 0 | F12: =F25 -> -17.73 | G12: =G25 -> -70.23 | H12: =H25 -> 0 | I12: =I25 -> 0 | J12: =J25 -> -14.620945 | ... P12: =P25 -> -59.194121
B13: Adjustments
D14: =D15-SUM(D10:D11) -> -16.81 | E14: =E15-SUM(E10:E11) -> -18.31 | F14: =F15-SUM(F10:F11) -> -739.28 | G14: =G15-SUM(G10:G11) -> 844.81 | H14: =H15-SUM(H10:H11) -> -647.08 | I14: =I15-SUM(I10:I11) -> -191.78
B15: Closing Balance | C15: ='Balance Sheet'!C49 -> 61.92 | D15: ='Balance Sheet'!D49 -> 766.06 | E15: ='Balance Sheet'!E49 -> 747.75 | F15: ='Balance Sheet'!F49 -> 706.99 | G15: ='Balance Sheet'!G49 -> 1551.8 | H15: ='Balance Sheet'!H49 -> 904.72 | I15: ='Balance Sheet'!I49 -> 712.94 | J15: =SUM(J10:J14) -> 1006.3023 | K15: =SUM(K10:K14) -> 1319.7246 | L15: =SUM(L10:L14) -> 1657.8317 | M15: =SUM(M10:M14) -> 2026.4159 | N15: =SUM(N10:N14) -> 2432.8094 | O15: =SUM(O10:O14) -> 2886.3974 | P15: =SUM(P10:P14) -> 3399.3367
B17: New Borrowings
B19: New Borrowings | C19: =CFS!C49 -> 0 | D19: =CFS!D49 -> 720.95 | E19: =CFS!E49 -> 0 | F19: =CFS!F49 -> 698.52 | G19: =CFS!G49 -> 0 | H19: =CFS!H49 -> 0 | I19: =CFS!I49 -> 0 | J19: =J21*$J20 -> 307.98329 | K19: =K21*$J20 -> 334.0595 | L19: =L21*$J20 -> 365.17192 | M19: =M21*$J20 -> 402.58299 | N19: =N21*$J20 -> 447.9511 | O19: =O21*$J20 -> 503.47995 | P19: =P21*$J20 -> 572.13348
B20: New Borrowing as a ( %) of revenue | C20: =C19/C21 -> 0 | D20: =D19/D21 -> 0.062153273 | E20: =E19/E21 -> 0 | F20: =F19/F21 -> 0.049413353 | G20: =G19/G21 -> 0 | H20: =H19/H21 -> 0 | I20: =I19/I21 -> 0 | J20: =AVERAGE(C20:I20) -> 0.015938089 | K20: 0.015938089 | L20: 0.015938089 | M20: 0.015938089 | N20: 0.015938089 | O20: 0.015938089 | P20: 0.015938089
B21: Revenue from operations | C21: ='Income Statement'!C10 -> 11054.67 | D21: ='Income Statement'!D10 -> 11599.55 | E21: ='Income Statement'!E10 -> 13136.14 | F21: ='Income Statement'!F10 -> 14136.26 | G21: ='Income Statement'!G10 -> 16300.55 | H21: ='Income Statement'!H10 -> 16769.27 | I21: ='Income Statement'!I10 -> 17942.67 | J21: ='Income Statement'!J10 -> 19323.727 | ... P21: ='Income Statement'!P10 -> 35897.244
B23: Repayment
B25: Repayment | C25: =CFS!C54 -> 0 | D25: =CFS!D54 -> 0 | E25: =CFS!E54 -> 0 | F25: =CFS!F54 -> -17.73 | G25: =CFS!G54 -> -70.23 | H25: =CFS!H54 -> 0 | I25: =CFS!I54 -> 0 | J25: =J10*$J26 -> -14.620945 | K25: =K10*$J26 -> -20.637208 | L25: =L10*$J26 -> -27.06486 | M25: =M10*$J26 -> -33.998746 | N25: =N10*$J26 -> -41.557656 | O25: =O10*$J26 -> -49.891957 | P25: =P10*$J26 -> -59.194121
B26: Repayment as a (%) of opening balance | D26: =D25/D10 -> 0 | E26: =E25/E10 -> 0 | F26: =F25/F10 -> -0.023711133 | G26: =G25/G10 -> -0.099336624 | H26: =H25/H10 -> 0 | I26: =I25/I10 -> 0 | J26: =AVERAGE(D26:I26) -> -0.02050796 | K26: -0.02050796 | L26: -0.02050796 | M26: -0.02050796 | N26: -0.02050796 | O26: -0.02050796 | P26: -0.02050796
B28: Finance Cost
B30: Finance cost | C30: ='Income Statement'!C19 -> 9.09 | D30: ='Income Statement'!D19 -> 76.9 | E30: ='Income Statement'!E19 -> 110.9 | F30: ='Income Statement'!F19 -> 144.29 | G30: ='Income Statement'!G19 -> 169.1 | H30: ='Income Statement'!H19 -> 164 | I30: ='Income Statement'!I19 -> 138.8 | J30: =J37*$J31 -> 124.53595 | K30: =K37*$J31 -> 187.7497 | L30: =L37*$J31 -> 279.95303 | M30: =M37*$J31 -> 420.59917 | N30: =N37*$J31 -> 642.57453 | O30: =O37*$J31 -> 1001.5613 | P30: =P37*$J31 -> 1591.9432
B31: Finance cost as a (%) of average debt | C31: =C30/C37 -> 0.13172004 | D31: =D30/D37 -> 0.093095329 | E31: =E30/E37 -> 0.061590239 | F31: =F30/F37 -> 0.063386423 | G31: =G30/G37 -> 0.062100054 | H31: =H30/H37 -> 0.065316266 | I31: =I30/I37 -> 0.084997459 | J31: =AVERAGE(C31:I31) -> 0.080315116 | K31: 0.080315116 | L31: 0.080315116 | M31: 0.080315116 | N31: 0.080315116 | O31: 0.080315116 | P31: 0.080315116
B34: Average debt
B35: Opening Balance | C35: =C10+C41 -> 0 | D35: =D10+D41 -> 138.02 | E35: =E10+E41 -> 1514.05 | F35: =F10+F41 -> 2087.17 | G35: =G10+G41 -> 2465.54 | H35: =H10+H41 -> 2980.51 | I35: =I10+I41 -> 2041.21 | J35: =J10+J41 -> 1224.77 | ... P35: =P10+P41 -> 15240.729
B36: Closing Balance | C36: =C44+C15 -> 138.02 | D36: =D44+D15 -> 1514.05 | E36: =E44+E15 -> 2087.17 | F36: =F44+F15 -> 2465.54 | G36: =G44+G15 -> 2980.51 | H36: =H44+H15 -> 2041.21 | I36: =I44+I15 -> 1224.77 | J36: =J44+J15 -> 1876.4133 | ... P36: =P44+P15 -> 24401.701
B37: Average Balance | C37: =AVERAGE(C35,C36) -> 69.01 | D37: =AVERAGE(D35,D36) -> 826.035 | E37: =AVERAGE(E35,E36) -> 1800.61 | F37: =AVERAGE(F35,F36) -> 2276.355 | G37: =AVERAGE(G35,G36) -> 2723.025 | H37: =AVERAGE(H35,H36) -> 2510.86 | I37: =AVERAGE(I35,I36) -> 1632.99 | J37: =AVERAGE(J35,J36) -> 1550.5917 | ... P37: =AVERAGE(P35,P36) -> 19821.215
B40: Short-term Borrowings
B41: Opening Balance | D41: =C44 -> 76.1 | E41: =D44 -> 747.99 | F41: =E44 -> 1339.42 | G41: =F44 -> 1758.55 | H41: =G44 -> 1428.71 | I41: =H44 -> 1136.49 | J41: =I44 -> 511.83 | K41: =J44 -> 870.111 | ... P41: =O44 -> 12354.332
B42: Repayment/proceeds from current borrowings (net) | C42: =C46 -> -41.91 | D42: =D46 -> 640.722 | E42: =E46 -> 567.8 | F42: =F46 -> 0 | G42: =G46 -> 0 | H42: =H46 -> -1027.48 | I42: =I46 -> 26.26 | J42: =J46 -> 358.281 | ... P42: =P46 -> 8648.0324
B43: Adjustments | C43: =C44-(SUM(C41:C42)) -> 118.01 | D43: =D44-(SUM(D41:D42)) -> 31.168 | E43: =E44-(SUM(E41:E42)) -> 23.63 | F43: =F44-(SUM(F41:F42)) -> 419.13 | G43: =G44-(SUM(G41:G42)) -> -329.84 | H43: =H44-(SUM(H41:H42)) -> 735.26 | I43: =I44-(SUM(I41:I42)) -> -650.92
B44: Closing Balance | C44: ='Balance Sheet'!C64 -> 76.1 | D44: ='Balance Sheet'!D64 -> 747.99 | E44: ='Balance Sheet'!E64 -> 1339.42 | F44: ='Balance Sheet'!F64 -> 1758.55 | G44: ='Balance Sheet'!G64 -> 1428.71 | H44: ='Balance Sheet'!H64 -> 1136.49 | I44: ='Balance Sheet'!I64 -> 511.83 | J44: =SUM(J41:J43) -> 870.111 | K44: =SUM(K41:K43) -> 1479.1887 | L44: =SUM(L41:L43) -> 2514.6208 | M44: =SUM(M41:M43) -> 4274.8553 | N44: =SUM(N41:N43) -> 7267.2541 | O44: =SUM(O41:O43) -> 12354.332 | P44: =SUM(P41:P43) -> 21002.364
B46: Repayment/proceeds from current borrowings (net) | C46: =CFS!C55 -> -41.91 | D46: =CFS!D55 -> 640.722 | E46: =CFS!E55 -> 567.8 | F46: =CFS!F55 -> 0 | G46: =CFS!G55 -> 0 | H46: =CFS!H55 -> -1027.48 | I46: =CFS!I55 -> 26.26 | J46: =J41*J$47 -> 358.281 | K46: =K41*K$47 -> 609.0777 | L46: =L41*L$47 -> 1035.4321 | M46: =M41*M$47 -> 1760.2346 | N46: =N41*N$47 -> 2992.3987 | O46: =O41*O$47 -> 5087.0779 | P46: =P41*P$47 -> 8648.0324
B47: Repayment/proceeds from current borrowings (net) as a % of opening balance | D47: =D46/D41 -> 8.4194744 | E47: =E46/E41 -> 0.75910106 | F47: =F46/F41 -> 0 | G47: =G46/G41 -> 0 | H47: =H46/H41 -> -0.71916624 | I47: =I46/I41 -> 0.023106231 | J47: =70% -> 0.7 | K47: 0.7 | L47: 0.7 | M47: 0.7 | N47: 0.7 | O47: 0.7 | P47: 0.7

Sheet Working Capital Schedule
B1: Britannia Industries Limited
B2: WORKING CAPITAL SCHEDULE
B5: Particulars | C5: 2019 | D5: 2020 | E5: 2021 | F5: 2022 | G5: 2023 | H5: 2024 | I5: 2025 | J5: 2026 | K5: 2027 | L5: 2028 | M5: 2029 | N5: 2030 | O5: 2031 | P5: 2032
C6: Actual | D6: Actual | E6: Actual | F6: Actual | G6: Actual | H6: Actual | I6: Actual | J6: Forecast | K6: Forecast | L6: Forecast | M6: Forecast | N6: Forecast | O6: Forecast | P6: Forecast
B8: INVENTORY
B11: INVENTORY | C11: ='Balance Sheet'!C24 -> 781.38 | D11: ='Balance Sheet'!D24 -> 740.96 | E11: ='Balance Sheet'!E24 -> 1091.49 | F11: ='Balance Sheet'!F24 -> 1367.49 | G11: ='Balance Sheet'!G24 -> 1193.26 | H11: ='Balance Sheet'!H24 -> 1181.22 | I11: ='Balance Sheet'!I24 -> 1236.51 | J11: =J13*2-I11 -> 1527.6793 | K11: =K13*2-J11 -> 1626.7369 | L11: =L13*2-K11 -> 1673.1872 | M11: =M13*2-L11 -> 2030.8365 | N11: =N13*2-M11 -> 2250.8721 | O11: =O13*2-N11 -> 2470.0177 | P11: =P13*2-O11 -> 2783.9632
B13: Average Inventory | D13: =AVERAGE(C11:D11) -> 761.17 | E13: =AVERAGE(D11:E11) -> 916.225 | F13: =AVERAGE(E11:F11) -> 1229.49 | G13: =AVERAGE(F11:G11) -> 1280.375 | H13: =AVERAGE(G11:H11) -> 1187.24 | I13: =AVERAGE(H11:I11) -> 1208.865 | J13: =J15/J17 -> 1382.0947 | K13: =K15/K17 -> 1577.2081 | L13: =L15/L17 -> 1649.962 | M13: =M15/M17 -> 1852.0119 | N13: =N15/N17 -> 2140.8543 | O13: =O15/O17 -> 2360.4449 | P13: =P15/P17 -> 2626.9905
B15: COGS | C15: ='Income Statement'!C17 -> 6561.46 | D15: ='Income Statement'!D17 -> 6927.47 | E15: ='Income Statement'!E17 -> 7626.1 | F15: ='Income Statement'!F17 -> 8760.3 | G15: ='Income Statement'!G17 -> 9591.3 | H15: ='Income Statement'!H17 -> 9492.03 | I15: ='Income Statement'!I17 -> 10604.05 | J15: ='Income Statement'!J17 -> 11242.782 | ... P15: ='Income Statement'!P17 -> 21179.374
B17: Invetory Turnover Ratio | D17: =D15/D13 -> 9.1010812 | E17: =E15/E13 -> 8.3233922 | F17: =F15/F13 -> 7.1251495 | G17: =G15/G13 -> 7.4910085 | H17: =H15/H13 -> 7.9950389 | I17: =I15/I13 -> 8.7719059 | J17: =AVERAGE(D17:I17) -> 8.134596 | K17: =AVERAGE(E17:J17) -> 7.9735152 | L17: =AVERAGE(F17:K17) -> 7.9152023 | M17: =AVERAGE(G17:L17) -> 8.0468778 | N17: =AVERAGE(H17:M17) -> 8.1395227 | O17: =AVERAGE(I17:N17) -> 8.1636033 | P17: =AVERAGE(J17:O17) -> 8.0622195
B19: Holding period | D19: =365/D17 -> 40.105125 | E19: =365/E17 -> 43.852313 | F19: =365/F17 -> 51.226996 | G19: =365/G17 -> 48.725082 | H19: =365/H17 -> 45.653311 | I19: =365/I17 -> 41.610114 | J19: =365/J17 -> 44.870083 | K19: =365/K17 -> 45.776548 | ... P19: =365/P17 -> 45.272893
B21: TRADE RECEIVABLE
B24: TRADE RECEIVABLE | C24: ='Balance Sheet'!C27 -> 394.24 | D24: ='Balance Sheet'!D27 -> 320.36 | E24: ='Balance Sheet'!E27 -> 257.27 | F24: ='Balance Sheet'!F27 -> 331.93 | G24: ='Balance Sheet'!G27 -> 328.94 | H24: ='Balance Sheet'!H27 -> 393.33 | I24: ='Balance Sheet'!I27 -> 448.61 | J24: =J26*2-I24 -> 428.67911 | K24: =K26*2-J24 -> 522.88797 | L24: =L26*2-K24 -> 517.30271 | M24: =M26*2-L24 -> 629.45323 | N24: =N26*2-M24 -> 646.5336 | O24: =O26*2-N24 -> 787.62691 | P24: =P26*2-O24 -> 842.09291
B26: Average Trade receivables | D26: =AVERAGE(C24:D24) -> 357.3 | E26: =AVERAGE(D24:E24) -> 288.815 | F26: =AVERAGE(E24:F24) -> 294.6 | G26: =AVERAGE(F24:G24) -> 330.435 | H26: =AVERAGE(G24:H24) -> 361.135 | I26: =AVERAGE(H24:I24) -> 420.97 | J26: =J28/J30 -> 438.64455 | K26: =K28/K30 -> 475.78354 | L26: =L28/L30 -> 520.09534 | M26: =M28/M30 -> 573.37797 | N26: =N28/N30 -> 637.99341 | O26: =O28/O30 -> 717.08026 | P26: =P28/P30 -> 814.85991
B28: Sales | C28: ='Income Statement'!C10 -> 11054.67 | D28: ='Income Statement'!D10 -> 11599.55 | E28: ='Income Statement'!E10 -> 13136.14 | F28: ='Income Statement'!F10 -> 14136.26 | G28: ='Income Statement'!G10 -> 16300.55 | H28: ='Income Statement'!H10 -> 16769.27 | I28: ='Income Statement'!I10 -> 17942.67 | J28: ='Income Statement'!J10 -> 19323.727 | ... P28: ='Income Statement'!P10 -> 35897.244
B30: Receivable Turnover Ratio | D30: =D28/D26 -> 32.464456 | E30: =E28/E26 -> 45.482887 | F30: =F28/F26 -> 47.984589 | G30: =G28/G26 -> 49.330579 | H30: =H28/H26 -> 46.434907 | I30: =I28/I26 -> 42.622206 | J30: =AVERAGE(D30:I30) -> 44.053271 | K30: 44.053271 | L30: 44.053271 | M30: 44.053271 | N30: 44.053271 | O30: 44.053271 | P30: 44.053271
B32: Receivable Collection Period | D32: =365/D30 -> 11.243065 | E32: =365/E30 -> 8.0249963 | F32: =365/F30 -> 7.6066088 | G32: =365/G30 -> 7.3990617 | H32: =365/H30 -> 7.8604659 | I32: =365/I30 -> 8.5636112 | J32: =365/J30 -> 8.2854234 | K32: =365/K30 -> 8.2854234 | ... P32: =365/P30 -> 8.2854234
B34: TRADE PAYABLES
B37: TRADE PAYABLES | C37: =C52 -> 1140.51 | D37: =D52 -> 1047 | E37: =E52 -> 1314.75 | F37: =F52 -> 1322.81 | G37: =G52 -> 1448.81 | H37: =H52 -> 1627.48 | I37: =I52 -> 1752.23 | J37: =J39*2-I37 -> 1865.4598 | K37: =K39*2-J37 -> 2181.1969 | L37: =L39*2-K37 -> 2021.1656 | M37: =M39*2-L37 -> 2774.2771 | N37: =N39*2-M37 -> 2832.891 | O37: =O39*2-N37 -> 3367.703 | P37: =P39*2-O37 -> 3447.3723
B39: Average Trade payables | D39: =AVERAGE(C52,D52) -> 1093.755 | E39: =AVERAGE(D52,E52) -> 1180.875 | F39: =AVERAGE(E52,F52) -> 1318.78 | G39: =AVERAGE(F52,G52) -> 1385.81 | H39: =AVERAGE(G52,H52) -> 1538.145 | I39: =AVERAGE(H52,I52) -> 1689.855 | J39: =J41/J43 -> 1808.8449 | K39: =K41/K43 -> 2023.3283 | L39: =L41/L43 -> 2101.1813 | M39: =M41/M43 -> 2397.7214 | N39: =N41/N43 -> 2803.5841 | O39: =O41/O43 -> 3100.297 | P39: =P41/P43 -> 3407.5377
B41: Purchases | C41: ='Income Statement'!C15 -> 1103.63 | D41: ='Income Statement'!D15 -> 973.74 | E41: ='Income Statement'!E15 -> 1160.89 | F41: ='Income Statement'!F15 -> 1361.59 | G41: ='Income Statement'!G15 -> 1337.13 | H41: ='Income Statement'!H15 -> 941.48 | I41: ='Income Statement'!I15 -> 809.35 | J41: ='Income Statement'!J15 -> 1495.8295 | ... P41: ='Income Statement'!P15 -> 2817.8731
B43: Payable Turnover Ratio | D43: =D41/D39 -> 0.8902725 | E43: =E41/E39 -> 0.98307611 | F43: =F41/F39 -> 1.0324618 | G43: =G41/G39 -> 0.96487253 | H43: =H41/H39 -> 0.61208794 | I43: =I41/I39 -> 0.47894642 | J43: =AVERAGE(D43:I43) -> 0.82695289 | K43: 0.82695289 | L43: 0.82695289 | M43: 0.82695289 | N43: 0.82695289 | O43: 0.82695289 | P43: 0.82695289
B45: Payable Payment Period | D45: =365/D43 -> 409.98683 | E45: =365/E43 -> 371.28356 | F45: =365/F43 -> 353.52397 | G45: =365/G43 -> 378.28831 | H45: =365/H43 -> 596.31954 | I45: =365/I43 -> 762.08942 | J45: =365/J43 -> 441.37944 | K45: =365/K43 -> 441.37944 | ... P45: =365/P43 -> 441.37944
B47: Composition of trade payables :
B49: (i) total outstanding dues of micro enterprises and small enterprises | C49: ='Balance Sheet'!C58 -> 1.78 | D49: ='Balance Sheet'!D58 -> 8.53 | E49: ='Balance Sheet'!E58 -> 28.44 | F49: ='Balance Sheet'!F58 -> 62.76 | G49: ='Balance Sheet'!G58 -> 43.92 | H49: ='Balance Sheet'!H58 -> 30.83 | I49: ='Balance Sheet'!I58 -> 27.83 | J49: =J52*$J56 -> 38.354995 | K49: =K52*$J56 -> 44.846744 | L49: =L52*$J56 -> 41.556402 | M49: =M52*$J56 -> 57.040836 | N49: =N52*$J56 -> 58.245974 | O49: =O52*$J56 -> 69.242035 | P49: =P52*$J56 -> 70.880086
B50: (ii) total outstanding dues of creditors other than micro enterprises an | C50: ='Balance Sheet'!C59 -> 1138.73 | D50: ='Balance Sheet'!D59 -> 1038.47 | E50: ='Balance Sheet'!E59 -> 1286.31 | F50: ='Balance Sheet'!F59 -> 1260.05 | G50: ='Balance Sheet'!G59 -> 1404.89 | H50: ='Balance Sheet'!H59 -> 1596.65 | I50: ='Balance Sheet'!I59 -> 1724.4 | J50: =J52*$J57 -> 1827.1048 | K50: =K52*$J57 -> 2136.3502 | L50: =L52*$J57 -> 1979.6092 | M50: =M52*$J57 -> 2717.2363 | N50: =N52*$J57 -> 2774.6451 | O50: =O52*$J57 -> 3298.4609 | P50: =P52*$J57 -> 3376.4923
B52: TOTAL | C52: =SUM(C49:C50) -> 1140.51 | D52: =SUM(D49:D50) -> 1047 | E52: =SUM(E49:E50) -> 1314.75 | F52: =SUM(F49:F50) -> 1322.81 | G52: =SUM(G49:G50) -> 1448.81 | H52: =SUM(H49:H50) -> 1627.48 | I52: =SUM(I49:I50) -> 1752.23 | J52: =J37 -> 1865.4598 | K52: =K37 -> 2181.1969 | L52: =L37 -> 2021.1656 | M52: =M37 -> 2774.2771 | N52: =N37 -> 2832.891 | O52: =O37 -> 3367.703 | P52: =P37 -> 3447.3723
B54: Composition of trade payables (%) :
B56: (i) total outstanding dues of micro enterprises and small enterprises | C56: =C49/C52 -> 0.0015607053 | D56: =D49/D52 -> 0.0081470869 | E56: =E49/E52 -> 0.021631489 | F56: =F49/F52 -> 0.047444455 | G56: =G49/G52 -> 0.030314534 | H56: =H49/H52 -> 0.018943397 | I56: =I49/I52 -> 0.015882618 | J56: =AVERAGE(C56:I56) -> 0.020560612 | K56: 0.020560612 | L56: 0.020560612 | M56: 0.020560612 | N56: 0.020560612 | O56: 0.020560612 | P56: 0.020560612
B57: (ii) total outstanding dues of creditors other than micro enterprises an | C57: =C50/C52 -> 0.99843929 | D57: =D50/D52 -> 0.99185291 | E57: =E50/E52 -> 0.97836851 | F57: =F50/F52 -> 0.95255554 | G57: =G50/G52 -> 0.96968547 | H57: =H50/H52 -> 0.9810566 | I57: =I50/I52 -> 0.98411738 | J57: =AVERAGE(C57:I57) -> 0.97943939 | K57: 0.97943939 | L57: 0.97943939 | M57: 0.97943939 | N57: 0.97943939 | O57: 0.97943939 | P57: 0.97943939
B59: TOTAL | C59: =SUM(C56:C57) -> 1 | D59: =SUM(D56:D57) -> 1 | E59: =SUM(E56:E57) -> 1 | F59: =SUM(F56:F57) -> 1 | G59: =SUM(G56:G57) -> 1 | H59: =SUM(H56:H57) -> 1 | I59: =SUM(I56:I57) -> 1 | J59: =SUM(J56:J57) -> 1 | ... P59: =SUM(P56:P57) -> 1

Sheet Other Schedule
B1: Britannia Industries Limited
B2: OTHER SCHEDULE
B5: Particulars | C5: 2019 | D5: 2020 | E5: 2021 | F5: 2022 | G5: 2023 | H5: 2024 | I5: 2025 | J5: 2026 | K5: 2027 | L5: 2028 | M5: 2029 | N5: 2030 | O5: 2031 | P5: 2032
C6: Actual | D6: Actual | E6: Actual | F6: Actual | G6: Actual | H6: Actual | I6: Actual | J6: Forecast | K6: Forecast | L6: Forecast | M6: Forecast | N6: Forecast | O6: Forecast | P6: Forecast
B8: Other Income
B10: Interest income | C10: =CFS!C40 -> 116.88 | D10: =CFS!D40 -> 127.62 | E10: =CFS!E40 -> 233.43 | F10: =CFS!F40 -> 206.75 | G10: =CFS!G40 -> 174.68 | H10: =CFS!H40 -> 170.26 | I10: =CFS!I40 -> 151.36 | J10: =J16 -> 217.3739 | K10: =K16 -> 573.46707 | L10: =L16 -> 1088.58 | M10: =M16 -> 1846.3069 | N10: =N16 -> 2840.0587 | O10: =O16 -> 4267.4362 | P10: =P16 -> 6506.7114
B11: Adjustments | C11: =C13-C10 -> 89.57 | D11: =D13-D10 -> 151.78 | E11: =E13-E10 -> 79.44 | F11: =F13-F10 -> 16.08 | G11: =G13-G10 -> 41.18 | H11: =H13-H10 -> 43.92 | I11: =I13-I10 -> 75.73
B13: Total Interest | C13: ='Income Statement'!C11 -> 206.45 | D13: ='Income Statement'!D11 -> 279.4 | E13: ='Income Statement'!E11 -> 312.87 | F13: ='Income Statement'!F11 -> 222.83 | G13: ='Income Statement'!G11 -> 215.86 | H13: ='Income Statement'!H11 -> 214.18 | I13: ='Income Statement'!I11 -> 227.09 | J13: =SUM(J10) -> 217.3739 | K13: =SUM(K10) -> 573.46707 | L13: =SUM(L10) -> 1088.58 | M13: =SUM(M10) -> 1846.3069 | N13: =SUM(N10) -> 2840.0587 | O13: =SUM(O10) -> 4267.4362 | P13: =SUM(P10) -> 6506.7114
B16: Interest Income | C16: =C10 -> 116.88 | D16: =D10 -> 127.62 | E16: =E10 -> 233.43 | F16: =F10 -> 206.75 | G16: =G10 -> 174.68 | H16: =H10 -> 170.26 | I16: =I10 -> 151.36 | J16: =J24*J17 -> 217.3739 | K16: =K24*K17 -> 573.46707 | L16: =L24*L17 -> 1088.58 | M16: =M24*M17 -> 1846.3069 | N16: =N24*N17 -> 2840.0587 | O16: =O24*O17 -> 4267.4362 | P16: =P24*P17 -> 6506.7114
B17: Interest income as % of Average Interest Earnings & Cash and Cash Equivalet | D17: =D16/D24 -> 0.092188668 | E17: =E16/E24 -> 0.17495943 | F17: =F16/F24 -> 0.18664969 | G17: =G16/G24 -> 0.18476053 | H17: =H16/H24 -> 0.18768361 | I17: =I16/I24 -> 0.23397201 | J17: =AVERAGE(D17:I17) -> 0.17670232 | K17: 0.17670232 | L17: 0.17670232 | M17: 0.17670232 | N17: 0.17670232 | O17: 0.17670232 | P17: 0.17670232
J18: 209.832 | K18: 573.46561 | L18: 1088.5837 | M18: 1846.3108 | N18: 2840.0584 | O18: 4267.4366 | P18: 6506.7073
B20: Interest income as % of Average Interest Earnings & Cash and Cash Equivalet
B22: Opening Balance | D22: =C23 -> 1332.76 | E22: =D23 -> 1435.91 | F22: =E23 -> 1232.48 | G22: =F23 -> 982.9 | H22: =G23 -> 907.98 | I22: =H23 -> 906.35 | J22: =I23 -> 387.48 | K22: =J23 -> 2072.86 | ... P22: =O23 -> 29149.95
B23: Closing Balance | C23: ='Balance Sheet'!C16+SUM('Balance Sheet'!C28:C30) -> 1332.76 | D23: ='Balance Sheet'!D16+SUM('Balance Sheet'!D28:D30) -> 1435.91 | E23: ='Balance Sheet'!E16+SUM('Balance Sheet'!E28:E30) -> 1232.48 | F23: ='Balance Sheet'!F16+SUM('Balance Sheet'!F28:F30) -> 982.9 | G23: ='Balance Sheet'!G16+SUM('Balance Sheet'!G28:G30) -> 907.98 | H23: ='Balance Sheet'!H16+SUM('Balance Sheet'!H28:H30) -> 906.35 | I23: ='Balance Sheet'!I16+SUM('Balance Sheet'!I28:I30) -> 387.48 | J23: ='Balance Sheet'!J16+SUM('Balance Sheet'!J28:J30) -> 2072.86 | ... P23: ='Balance Sheet'!P16+SUM('Balance Sheet'!P28:P30) -> 44496.07
B24: Average Balance | D24: =AVERAGE(D22:D23) -> 1384.335 | E24: =AVERAGE(E22:E23) -> 1334.195 | F24: =AVERAGE(F22:F23) -> 1107.69 | G24: =AVERAGE(G22:G23) -> 945.44 | H24: =AVERAGE(H22:H23) -> 907.165 | I24: =AVERAGE(I22:I23) -> 646.915 | J24: =AVERAGE(J22:J23) -> 1230.17 | K24: =AVERAGE(K22:K23) -> 3245.385 | ... P24: =AVERAGE(P22:P23) -> 36823.01

Sheet DCF
B1: Britannia Industries Limited
B2: DISCOUNTED CASH FLOW
B5: Particulars | C5: 2019 | D5: 2020 | E5: 2021 | F5: 2022 | G5: 2023 | H5: 2024 | I5: 2025 | J5: 2026 | K5: 2027 | L5: 2028 | M5: 2029 | N5: 2030 | O5: 2031 | P5: 2032
C6: Actual | D6: Actual | E6: Actual | F6: Actual | G6: Actual | H6: Actual | I6: Actual | J6: Forecast | K6: Forecast | L6: Forecast | M6: Forecast | N6: Forecast | O6: Forecast | P6: Forecast
B7: EBIT | I7: ='Income Statement'!I19+'Income Statement'!I27 -> 3065.37 | J7: ='Income Statement'!J19+'Income Statement'!J27 -> 4044.3812 | K7: ='Income Statement'!K19+'Income Statement'!K27 -> 4311.8216 | L7: ='Income Statement'!L19+'Income Statement'!L27 -> 5834.3923 | M7: ='Income Statement'!M19+'Income Statement'!M27 -> 6548.8927 | N7: ='Income Statement'!N19+'Income Statement'!N27 -> 7208.947 | O7: ='Income Statement'!O19+'Income Statement'!O27 -> 9476.0323 | P7: ='Income Statement'!P19+'Income Statement'!P27 -> 13128.315
B8: Tax Rate | I8: ='Cost Schedule '!I33 -> 0.25583191 | J8: ='Cost Schedule '!J33 -> 0.25752762 | K8: ='Cost Schedule '!K33 -> 0.25752762 | L8: ='Cost Schedule '!L33 -> 0.25752762 | M8: ='Cost Schedule '!M33 -> 0.25752762 | N8: ='Cost Schedule '!N33 -> 0.25752762 | O8: ='Cost Schedule '!O33 -> 0.25752762 | P8: ='Cost Schedule '!P33 -> 0.25752762
B10: EBIT*(1-tax rate) | I10: =I7*(1-I8) -> 2281.1505 | J10: =J7*(1-J8) -> 3002.8413 | K10: =K7*(1-K8) -> 3201.4084 | L10: =L7*(1-L8) -> 4331.8752 | M10: =M7*(1-M8) -> 4862.372 | N10: =N7*(1-N8) -> 5352.444 | O10: =O7*(1-O8) -> 7035.6923 | P10: =P7*(1-P8) -> 9747.411
B11: Less: Capital Expenditure | I11: =-('Asset Schedule'!I16) -> -374.85 | J11: =-('Asset Schedule'!J16) -> -195.42542 | K11: =-('Asset Schedule'!K16) -> -229.78572 | L11: =-('Asset Schedule'!L16) -> -275.87598 | M11: =-('Asset Schedule'!M16) -> -338.8667 | N11: =-('Asset Schedule'!N16) -> -417.5453 | O11: =-('Asset Schedule'!O16) -> -505.54575 | P11: =-('Asset Schedule'!P16) -> -616.84705
B12: Add:(increase)/decrease in Working Capital | I12: =SUM(CFS!I18:I21) -> -4.2 | J12: =SUM(CFS!J18:J21) -> -158.00868 | K12: =SUM(CFS!K18:K21) -> 122.47078 | L12: =SUM(CFS!L18:L21) -> -200.89644 | M12: =SUM(CFS!M18:M21) -> 283.31178 | N12: =SUM(CFS!N18:N21) -> -178.50204 | O12: =SUM(CFS!O18:O21) -> 174.57297 | P12: =SUM(CFS!P18:P21) -> -288.74217
B13: Add:Non Cash charges | I13: =CFS!I9 -> 313.34 | J13: =CFS!J9 -> 281.33107 | K13: =CFS!K9 -> 273.68575 | L13: =CFS!L9 -> 271.10684 | M13: =CFS!M9 -> 274.63999 | N13: =CFS!N9 -> 285.11669 | O13: =CFS!O9 -> 302.69535 | P13: =CFS!P9 -> 328.79864
B14: Free Cash Flow to Firm | I14: =SUM(I10:I13) -> 2215.4405 | J14: =SUM(J10:J13) -> 2930.7383 | K14: =SUM(K10:K13) -> 3367.7792 | L14: =SUM(L10:L13) -> 4126.2096 | M14: =SUM(M10:M13) -> 5081.457 | N14: =SUM(N10:N13) -> 5041.5134 | O14: =SUM(O10:O13) -> 7007.4148 | P14: =SUM(P10:P13) -> 9170.6205
B16: COST OF EQUITY
B17: Risk free Rate | I17: 0.067 | J17: 0.067 | K17: 0.067 | L17: 0.067 | M17: 0.067 | N17: 0.067 | O17: 0.067 | P17: 0.067
B18: Expected return from the market | I18: ='Income Statement'!I32/'Income Statement'!I10 -> 0.12137881 | J18: ='Income Statement'!J32/'Income Statement'!J10 -> 0.15061157 | K18: ='Income Statement'!K32/'Income Statement'!K10 -> 0.14608949 | L18: ='Income Statement'!L32/'Income Statement'!L10 -> 0.17999457 | M18: ='Income Statement'!M32/'Income Statement'!M10 -> 0.18013608 | N18: ='Income Statement'!N32/'Income Statement'!N10 -> 0.17346484 | O18: ='Income Statement'!O32/'Income Statement'!O10 -> 0.19918057 | P18: ='Income Statement'!P32/'Income Statement'!P10 -> 0.23860988
B19: Market Premium | I19: =I18-I17 -> 0.054378814 | J19: =J18-J17 -> 0.083611567 | K19: =K18-K17 -> 0.079089485 | L19: =L18-L17 -> 0.11299457 | M19: =M18-M17 -> 0.11313608 | N19: =N18-N17 -> 0.10646484 | O19: =O18-O17 -> 0.13218057 | P19: =P18-P17 -> 0.17160988
B20: Beta | I20: 0.52 | J20: 0.52 | K20: 0.52 | L20: 0.52 | M20: 0.52 | N20: 0.52 | O20: 0.52 | P20: 0.52
B22: Cost Of Equity ( CAPM) | I22: =I17+(I20*I19) -> 0.095276983 | J22: =J17+(J20*J19) -> 0.11047801 | K22: =K17+(K20*K19) -> 0.10812653 | L22: =L17+(L20*L19) -> 0.12575718 | M22: =M17+(M20*M19) -> 0.12583076 | N22: =N17+(N20*N19) -> 0.12236172 | O22: =O17+(O20*O19) -> 0.1357339 | P22: =P17+(P20*P19) -> 0.15623714
B24: COST OF DEBT
B25: Interest rate on debt | I25: ='Debt Schedule'!I30/'Debt Schedule'!I36 -> 0.1133274 | J25: ='Debt Schedule'!J30/'Debt Schedule'!J36 -> 0.066369145 | K25: ='Debt Schedule'!K30/'Debt Schedule'!K36 -> 0.067079498 | L25: ='Debt Schedule'!L30/'Debt Schedule'!L36 -> 0.067095558 | M25: ='Debt Schedule'!M30/'Debt Schedule'!M36 -> 0.066748304 | N25: ='Debt Schedule'!N30/'Debt Schedule'!N36 -> 0.066244363 | O25: ='Debt Schedule'!O30/'Debt Schedule'!O36 -> 0.065716102 | P25: ='Debt Schedule'!P30/'Debt Schedule'!P36 -> 0.065239025
B26: Tax Rate | I26: =I8 -> 0.25583191 | J26: =J8 -> 0.25752762 | K26: =K8 -> 0.25752762 | L26: =L8 -> 0.25752762 | M26: =M8 -> 0.25752762 | N26: =N8 -> 0.25752762 | O26: =O8 -> 0.25752762 | P26: =P8 -> 0.25752762
B28: Cost of debt | I28: =I25*(1-I26) -> 0.084334635 | J28: =J25*(1-J26) -> 0.049277257 | K28: =K25*(1-K26) -> 0.049804675 | L28: =L25*(1-L26) -> 0.049816598 | M28: =M25*(1-M26) -> 0.049558772 | N28: =N25*(1-N26) -> 0.04918461 | O28: =O25*(1-O26) -> 0.048792391 | P28: =P25*(1-P26) -> 0.048438174
B30: Total Debt | I30: ='Debt Schedule'!I36 -> 1224.77 | J30: ='Debt Schedule'!J36 -> 1876.4133 | K30: ='Debt Schedule'!K36 -> 2798.9133 | L30: ='Debt Schedule'!L36 -> 4172.4525 | M30: ='Debt Schedule'!M36 -> 6301.2713 | N30: ='Debt Schedule'!N36 -> 9700.0635 | O30: ='Debt Schedule'!O36 -> 15240.729 | P30: ='Debt Schedule'!P36 -> 24401.701
B31: Total Equity | I31: ='Balance Sheet'!I42 -> 4355.72 | J31: ='Balance Sheet'!J42 -> 5430.0643 | K31: ='Balance Sheet'!K42 -> 6656.0413 | L31: ='Balance Sheet'!L42 -> 8944.0266 | M31: ='Balance Sheet'!M42 -> 11658.083 | N31: ='Balance Sheet'!N42 -> 14697.4 | O31: ='Balance Sheet'!O42 -> 19153.429 | P31: ='Balance Sheet'!P42 -> 25882.833
B33: TOTAL | I33: =SUM(I30:I31) -> 5580.49 | J33: =SUM(J30:J31) -> 7306.4777 | K33: =SUM(K30:K31) -> 9454.9546 | L33: =SUM(L30:L31) -> 13116.479 | M33: =SUM(M30:M31) -> 17959.354 | N33: =SUM(N30:N31) -> 24397.464 | O33: =SUM(O30:O31) -> 34394.158 | P33: =SUM(P30:P31) -> 50284.534
B35: %of Debt | I35: =I30/I33 -> 0.21947356 | J35: =J30/J33 -> 0.25681504 | K35: =K30/K33 -> 0.2960261 | L35: =L30/L33 -> 0.31810766 | M35: =M30/M33 -> 0.35086291 | N35: =N30/N33 -> 0.39758491 | O35: =O30/O33 -> 0.44311971 | P35: =P30/P33 -> 0.48527249
B36: %of Equity | I36: =I31/I33 -> 0.78052644 | J36: =J31/J33 -> 0.74318496 | K36: =K31/K33 -> 0.7039739 | L36: =L31/L33 -> 0.68189234 | M36: =M31/M33 -> 0.64913709 | N36: =N31/N33 -> 0.60241509 | O36: =O31/O33 -> 0.55688029 | P36: =P31/P33 -> 0.51472751
I37: =SUM(I35:I36) -> 1 | J37: =SUM(J35:J36) -> 1 | K37: =SUM(K35:K36) -> 1 | L37: =SUM(L35:L36) -> 1 | M37: =SUM(M35:M36) -> 1 | N37: =SUM(N35:N36) -> 1 | O37: =SUM(O35:O36) -> 1 | P37: =SUM(P35:P36) -> 1
B39: WACC | I39: =I35*I28+(I36*I22) -> 0.092875427 | J39: =J35*J28+(J36*J22) -> 0.09476074 | K39: =K35*K28+(K36*K22) -> 0.09086174 | L39: =L35*L28+(L36*L22) -> 0.1015999 | M39: =M35*M28+(M36*M22) -> 0.099069749 | N39: =N35*N28+(N36*N22) -> 0.093267604 | O39: =O35*O28+(O36*O22) -> 0.097208403 | P39: =P35*P28+(P36*P22) -> 0.10392527
B41: THEORETICAL WACC | I41: =AVERAGE(I39:O39) -> 0.095663366
B43: NPV of Business | I43: =NPV(I41,I14:P14) -> 24131.312
B46: Long Term Free Cash Flow Growth Assumptions | I46: 0.04 | P46: =P14*(1+I46)/(I41-I46) -> 171341.51
B47: Terminal Value
B49: NPV of Business Terminal Value | I49: =P46/(1+I41)^5 -> 108511.78
B51: Enterprise Value | I51: =I43+I49 -> 132643.09
B52: Add: Cash and Cash Equivalent & Bank Balance (opening balance) | I52: ='Balance Sheet'!H28 -> 322.8
B53: Less: Minority Interest ( Opening Balance) | I53: ='Income Statement'!H41 -> -5.59
B54: Less: Debt ( Beginning Balance) | I54: =-('Debt Schedule'!I35) -> -2041.21
B55: Equity Value | I55: =SUM(I51:I54) -> 130919.09
B57: Number of shares outstanding | I57: ='Balance Sheet'!I40/1 -> 24.09
B58: Price per share | I58: =I55/I57 -> 5434.5825
B59: MPS as on 28/12/2025 | I59: 6014.5
